{
 "AssignmentId": "3RXCAC0YISDF2761MOFRK8KQ1L1G81",
 "WorkerId": "bedcc2096ab97bb7cd9b7fdc9db564b7",
 "HITId": "3EKZL9T8Y8ASRMTWX48CJAWNY5AHCG",
 "AssignmentStatus": "Submitted",
 "AutoApprovalTime": "2019-05-20T14:18:10.000Z",
 "AcceptTime": "2019-05-19T14:07:59.000Z",
 "SubmitTime": "2019-05-19T14:18:10.000Z",
 "answers": {
  "trials": [
   {
    "trial_type": "filler",
    "page_type": "text",
    "condition": "uninterrupted",
    "chapter_num": 0,
    "page_num": 0,
    "page_content": "Dax is a lot like Earth.  Like Earth it has seven continents, in similar locations, but instead of North ",
    "response_1": -99,
    "response_2": -99,
    "rt": 9408,
    "kind": "NA",
    "predicate_1": "NA",
    "predicate_2": "NA",
    "question_order": "NA",
    "chapter": "An introduction to Dax",
    "quantifier": "generic"
   },
   {
    "trial_type": "filler",
    "page_type": "text",
    "condition": "uninterrupted",
    "chapter_num": 0,
    "page_num": 1,
    "page_content": " America, South America, Africa, Europe, Asia, Australia, and Antarctica, the continents are  ",
    "response_1": -99,
    "response_2": -99,
    "rt": 3562,
    "kind": "NA",
    "predicate_1": "NA",
    "predicate_2": "NA",
    "question_order": "NA",
    "chapter": "An introduction to Dax",
    "quantifier": "generic"
   },
   {
    "trial_type": "filler",
    "page_type": "text",
    "condition": "uninterrupted",
    "chapter_num": 0,
    "page_num": 2,
    "page_content": " called  Aga,  Benli, Caro, Dodi, Ente, Fale, and Gomi. Its climate is a lot like Earth's, too. But the",
    "response_1": -99,
    "response_2": -99,
    "rt": 7098,
    "kind": "NA",
    "predicate_1": "NA",
    "predicate_2": "NA",
    "question_order": "NA",
    "chapter": "An introduction to Dax",
    "quantifier": "generic"
   },
   {
    "trial_type": "filler",
    "page_type": "text",
    "condition": "uninterrupted",
    "chapter_num": 0,
    "page_num": 3,
    "page_content": "  plants and animals of Dax are quite different.",
    "response_1": -99,
    "response_2": -99,
    "rt": 2692,
    "kind": "NA",
    "predicate_1": "NA",
    "predicate_2": "NA",
    "question_order": "NA",
    "chapter": "An introduction to Dax",
    "quantifier": "generic"
   },
   {
    "trial_type": "filler",
    "page_type": "text",
    "condition": "uninterrupted",
    "chapter_num": 1,
    "page_num": 0,
    "page_content": "Zorxon is the overlord of Dax.  Everyone loves Zorxon because she ",
    "response_1": -99,
    "response_2": -99,
    "rt": 6548,
    "kind": "aliens",
    "predicate_1": "love Zorxon",
    "predicate_2": "are provided for by Zorxon",
    "question_order": "NA",
    "chapter": "Zorxon, overlord of Dax",
    "quantifier": "all"
   },
   {
    "trial_type": "filler",
    "page_type": "text",
    "condition": "uninterrupted",
    "chapter_num": 1,
    "page_num": 1,
    "page_content": "provides for all the aliens of Dax. However, Zorxon is now very old ",
    "response_1": -99,
    "response_2": -99,
    "rt": 3677,
    "kind": "aliens",
    "predicate_1": "love Zorxon",
    "predicate_2": "are provided for by Zorxon",
    "question_order": "NA",
    "chapter": "Zorxon, overlord of Dax",
    "quantifier": "all"
   },
   {
    "trial_type": "filler",
    "page_type": "text",
    "condition": "uninterrupted",
    "chapter_num": 1,
    "page_num": 2,
    "page_content": "and she rarely makes public appearances anymore. Still, she is very influential.",
    "response_1": -99,
    "response_2": -99,
    "rt": 3635,
    "kind": "aliens",
    "predicate_1": "love Zorxon",
    "predicate_2": "are provided for by Zorxon",
    "question_order": "NA",
    "chapter": "Zorxon, overlord of Dax",
    "quantifier": "all"
   },
   {
    "trial_type": "filler",
    "page_type": "query",
    "condition": "uninterrupted",
    "chapter_num": 1,
    "page_num": 3,
    "page_content": "",
    "query_predicate_1": "love Zorxon",
    "query_predicate_2": "are provided for by Zorxon",
    "response_1": 0.97,
    "response_2": 0.98,
    "rt": 6479,
    "kind": "aliens",
    "predicate_1": "love Zorxon",
    "predicate_2": "are provided for by Zorxon",
    "question_order": "reverse",
    "chapter": "Zorxon, overlord of Dax",
    "quantifier": "all"
   },
   {
    "trial_type": "filler",
    "page_type": "text",
    "condition": "uninterrupted",
    "chapter_num": 2,
    "page_num": 0,
    "page_content": "Wopis are extremely rare creatures. They only live in the desert and ",
    "query_predicate_1": "love Zorxon",
    "query_predicate_2": "are provided for by Zorxon",
    "response_1": -99,
    "response_2": -99,
    "rt": 4392,
    "kind": "wopis",
    "predicate_1": "live in the desert",
    "predicate_2": "are very hard to find",
    "question_order": "reverse",
    "chapter": "Wopis",
    "quantifier": "all"
   },
   {
    "trial_type": "filler",
    "page_type": "text",
    "condition": "uninterrupted",
    "chapter_num": 2,
    "page_num": 1,
    "page_content": "they all are very hard to find. Wopis sleep during the day to avoid ",
    "query_predicate_1": "love Zorxon",
    "query_predicate_2": "are provided for by Zorxon",
    "response_1": -99,
    "response_2": -99,
    "rt": 3335,
    "kind": "wopis",
    "predicate_1": "live in the desert",
    "predicate_2": "are very hard to find",
    "question_order": "reverse",
    "chapter": "Wopis",
    "quantifier": "all"
   },
   {
    "trial_type": "filler",
    "page_type": "text",
    "condition": "uninterrupted",
    "chapter_num": 2,
    "page_num": 2,
    "page_content": "the heat, and look for food at night when it's cool.",
    "query_predicate_1": "love Zorxon",
    "query_predicate_2": "are provided for by Zorxon",
    "response_1": -99,
    "response_2": -99,
    "rt": 3211,
    "kind": "wopis",
    "predicate_1": "live in the desert",
    "predicate_2": "are very hard to find",
    "question_order": "reverse",
    "chapter": "Wopis",
    "quantifier": "all"
   },
   {
    "trial_type": "filler",
    "page_type": "query",
    "condition": "uninterrupted",
    "chapter_num": 2,
    "page_num": 3,
    "page_content": "",
    "query_predicate_1": "live in the desert",
    "query_predicate_2": "are very hard to find",
    "response_1": 0.51,
    "response_2": 0.77,
    "rt": 7451,
    "kind": "wopis",
    "predicate_1": "live in the desert",
    "predicate_2": "are very hard to find",
    "question_order": "same",
    "chapter": "Wopis",
    "quantifier": "all"
   },
   {
    "trial_type": "critical",
    "page_type": "text",
    "condition": "interrupted",
    "chapter_num": 3,
    "page_num": 0,
    "page_content": "Glippets are large creatures, quite intelligent, with a life-span of about ",
    "query_predicate_1": "live in the desert",
    "query_predicate_2": "are very hard to find",
    "response_1": -99,
    "response_2": -99,
    "rt": 4005,
    "kind": "glippets",
    "predicate_1": "live on the continent of Caro",
    "predicate_2": "live on the continent of Este",
    "question_order": "same",
    "chapter": "Glippets",
    "quantifier": "generic"
   },
   {
    "trial_type": "critical",
    "page_type": "text",
    "condition": "interrupted",
    "chapter_num": 3,
    "page_num": 1,
    "page_content": "sixty years. They live on the southern continent of Caro",
    "query_predicate_1": "live in the desert",
    "query_predicate_2": "are very hard to find",
    "response_1": -99,
    "response_2": -99,
    "rt": 4497,
    "kind": "glippets",
    "predicate_1": "live on the continent of Caro",
    "predicate_2": "live on the continent of Este",
    "question_order": "same",
    "chapter": "Glippets",
    "quantifier": "generic"
   },
   {
    "trial_type": "critical",
    "page_type": "query",
    "condition": "interrupted",
    "chapter_num": 3,
    "page_num": -1,
    "page_content": "",
    "query_predicate_1": "live on the continent of Caro",
    "query_predicate_2": "live on the continent of Este",
    "response_1": 0.87,
    "response_2": 0.07,
    "rt": 10563,
    "kind": "glippets",
    "predicate_1": "live on the continent of Caro",
    "predicate_2": "live on the continent of Este",
    "question_order": "same",
    "chapter": "Glippets",
    "quantifier": "generic"
   },
   {
    "trial_type": "critical",
    "page_type": "text",
    "condition": "interrupted",
    "chapter_num": 3,
    "page_num": 2,
    "page_content": "and enjoy the sunshine there.",
    "query_predicate_1": "live on the continent of Caro",
    "query_predicate_2": "live on the continent of Este",
    "response_1": 0.87,
    "response_2": 0.07,
    "rt": 1596,
    "kind": "glippets",
    "predicate_1": "live on the continent of Caro",
    "predicate_2": "live on the continent of Este",
    "question_order": "same",
    "chapter": "Glippets",
    "quantifier": "generic"
   },
   {
    "trial_type": "critical",
    "page_type": "text",
    "condition": "nme_interrupted",
    "chapter_num": 4,
    "page_num": 0,
    "page_content": "Lorches have massive beaks and are found on the continents of Dodi and Gomi. The two continents",
    "query_predicate_1": "live on the continent of Caro",
    "query_predicate_2": "live on the continent of Este",
    "response_1": -99,
    "response_2": -99,
    "rt": 5812,
    "kind": "lorches",
    "predicate_1": "have long wings",
    "predicate_2": "have short wings",
    "question_order": "same",
    "chapter": "Lorches",
    "quantifier": "generic"
   },
   {
    "trial_type": "critical",
    "page_type": "text",
    "condition": "nme_interrupted",
    "chapter_num": 4,
    "page_num": 1,
    "page_content": "are quite different in what kinds of animals are available for them to eat. Lorches have long wings ",
    "query_predicate_1": "live on the continent of Caro",
    "query_predicate_2": "live on the continent of Este",
    "response_1": -99,
    "response_2": -99,
    "rt": 4294,
    "kind": "lorches",
    "predicate_1": "have long wings",
    "predicate_2": "have short wings",
    "question_order": "same",
    "chapter": "Lorches",
    "quantifier": "generic"
   },
   {
    "trial_type": "critical",
    "page_type": "query",
    "condition": "nme_interrupted",
    "chapter_num": 4,
    "page_num": -1,
    "page_content": "",
    "query_predicate_1": "have long wings",
    "query_predicate_2": "have sharp claws",
    "response_1": 0.85,
    "response_2": 0.71,
    "rt": 8122,
    "kind": "lorches",
    "predicate_1": "have long wings",
    "predicate_2": "have short wings",
    "question_order": "same",
    "chapter": "Lorches",
    "quantifier": "generic"
   },
   {
    "trial_type": "critical",
    "page_type": "text",
    "condition": "nme_interrupted",
    "chapter_num": 4,
    "page_num": 2,
    "page_content": "and fly only at night.",
    "query_predicate_1": "have long wings",
    "query_predicate_2": "have sharp claws",
    "response_1": 0.85,
    "response_2": 0.71,
    "rt": 1453,
    "kind": "lorches",
    "predicate_1": "have long wings",
    "predicate_2": "have short wings",
    "question_order": "same",
    "chapter": "Lorches",
    "quantifier": "generic"
   },
   {
    "trial_type": "critical",
    "page_type": "text",
    "condition": "uninterrupted",
    "chapter_num": 5,
    "page_num": 0,
    "page_content": "Kaples are small animals that live in the jungles. They are most active ",
    "query_predicate_1": "have long wings",
    "query_predicate_2": "have sharp claws",
    "response_1": -99,
    "response_2": -99,
    "rt": 3785,
    "kind": "kaples",
    "predicate_1": "have striped fur",
    "predicate_2": "have spotted fur",
    "question_order": "same",
    "chapter": "Kaples",
    "quantifier": "generic"
   },
   {
    "trial_type": "critical",
    "page_type": "text",
    "condition": "uninterrupted",
    "chapter_num": 5,
    "page_num": 1,
    "page_content": "at dawn and at dusk, when their usual predators are less active. Their thick fur helps camouflage ",
    "query_predicate_1": "have long wings",
    "query_predicate_2": "have sharp claws",
    "response_1": -99,
    "response_2": -99,
    "rt": 4140,
    "kind": "kaples",
    "predicate_1": "have striped fur",
    "predicate_2": "have spotted fur",
    "question_order": "same",
    "chapter": "Kaples",
    "quantifier": "generic"
   },
   {
    "trial_type": "critical",
    "page_type": "text",
    "condition": "uninterrupted",
    "chapter_num": 5,
    "page_num": 2,
    "page_content": "them among the plants on the forest floor. Kaples have striped fur ",
    "query_predicate_1": "have long wings",
    "query_predicate_2": "have sharp claws",
    "response_1": -99,
    "response_2": -99,
    "rt": 2633,
    "kind": "kaples",
    "predicate_1": "have striped fur",
    "predicate_2": "have spotted fur",
    "question_order": "same",
    "chapter": "Kaples",
    "quantifier": "generic"
   },
   {
    "trial_type": "critical",
    "page_type": "text",
    "condition": "uninterrupted",
    "chapter_num": 5,
    "page_num": 3,
    "page_content": "and spotted fur.",
    "query_predicate_1": "have long wings",
    "query_predicate_2": "have sharp claws",
    "response_1": -99,
    "response_2": -99,
    "rt": 1368,
    "kind": "kaples",
    "predicate_1": "have striped fur",
    "predicate_2": "have spotted fur",
    "question_order": "same",
    "chapter": "Kaples",
    "quantifier": "generic"
   },
   {
    "trial_type": "critical",
    "page_type": "query",
    "condition": "uninterrupted",
    "chapter_num": 5,
    "page_num": 4,
    "page_content": "",
    "query_predicate_1": "have striped fur",
    "query_predicate_2": "have spotted fur",
    "response_1": 0.81,
    "response_2": 0.79,
    "rt": 5127,
    "kind": "kaples",
    "predicate_1": "have striped fur",
    "predicate_2": "have spotted fur",
    "question_order": "same",
    "chapter": "Kaples",
    "quantifier": "generic"
   },
   {
    "trial_type": "filler",
    "page_type": "text",
    "condition": "interrupted",
    "chapter_num": 6,
    "page_num": 0,
    "page_content": "Nannus only feed on rare flowers called lodeks. Most lodeks only ",
    "query_predicate_1": "have striped fur",
    "query_predicate_2": "have spotted fur",
    "response_1": -99,
    "response_2": -99,
    "rt": 4737,
    "kind": "lodeks",
    "predicate_1": "only bloom for one day a year",
    "predicate_2": "have purple petals",
    "question_order": "same",
    "chapter": "Nannus",
    "quantifier": "most"
   },
   {
    "trial_type": "filler",
    "page_type": "text",
    "condition": "interrupted",
    "chapter_num": 6,
    "page_num": 1,
    "page_content": "bloom for one day a year, and most have purple petals. The plant that ",
    "query_predicate_1": "have striped fur",
    "query_predicate_2": "have spotted fur",
    "response_1": -99,
    "response_2": -99,
    "rt": 3074,
    "kind": "lodeks",
    "predicate_1": "only bloom for one day a year",
    "predicate_2": "have purple petals",
    "question_order": "same",
    "chapter": "Nannus",
    "quantifier": "most"
   },
   {
    "trial_type": "filler",
    "page_type": "query",
    "condition": "interrupted",
    "chapter_num": 6,
    "page_num": -1,
    "page_content": "",
    "query_predicate_1": "only bloom for one day a year",
    "query_predicate_2": "have purple petals",
    "response_1": 0.74,
    "response_2": 0.53,
    "rt": 7060,
    "kind": "lodeks",
    "predicate_1": "only bloom for one day a year",
    "predicate_2": "have purple petals",
    "question_order": "same",
    "chapter": "Nannus",
    "quantifier": "most"
   },
   {
    "trial_type": "filler",
    "page_type": "text",
    "condition": "interrupted",
    "chapter_num": 6,
    "page_num": 2,
    "page_content": "lodeks grow on is hard to find because it only grows next to caves.",
    "query_predicate_1": "only bloom for one day a year",
    "query_predicate_2": "have purple petals",
    "response_1": 0.74,
    "response_2": 0.53,
    "rt": 2256,
    "kind": "lodeks",
    "predicate_1": "only bloom for one day a year",
    "predicate_2": "have purple petals",
    "question_order": "same",
    "chapter": "Nannus",
    "quantifier": "most"
   },
   {
    "trial_type": "critical",
    "page_type": "text",
    "condition": "uninterrupted",
    "chapter_num": 7,
    "page_num": 0,
    "page_content": "Batozes are large birds that are found along all the coasts of Dax. They are skilled hunters and ",
    "query_predicate_1": "only bloom for one day a year",
    "query_predicate_2": "have purple petals",
    "response_1": -99,
    "response_2": -99,
    "rt": 5047,
    "kind": "batozes",
    "predicate_1": "have six wings",
    "predicate_2": "have seven wings",
    "question_order": "same",
    "chapter": "Batozes",
    "quantifier": "generic"
   },
   {
    "trial_type": "critical",
    "page_type": "text",
    "condition": "uninterrupted",
    "chapter_num": 7,
    "page_num": 1,
    "page_content": "can fly for whole days without stopping. They use their sharp claws to hunt for fish. They also ",
    "query_predicate_1": "only bloom for one day a year",
    "query_predicate_2": "have purple petals",
    "response_1": -99,
    "response_2": -99,
    "rt": 4063,
    "kind": "batozes",
    "predicate_1": "have six wings",
    "predicate_2": "have seven wings",
    "question_order": "same",
    "chapter": "Batozes",
    "quantifier": "generic"
   },
   {
    "trial_type": "critical",
    "page_type": "text",
    "condition": "uninterrupted",
    "chapter_num": 7,
    "page_num": 2,
    "page_content": "have special wings that are light but powerful. Batozes have six wings ",
    "query_predicate_1": "only bloom for one day a year",
    "query_predicate_2": "have purple petals",
    "response_1": -99,
    "response_2": -99,
    "rt": 2358,
    "kind": "batozes",
    "predicate_1": "have six wings",
    "predicate_2": "have seven wings",
    "question_order": "same",
    "chapter": "Batozes",
    "quantifier": "generic"
   },
   {
    "trial_type": "critical",
    "page_type": "text",
    "condition": "uninterrupted",
    "chapter_num": 7,
    "page_num": 3,
    "page_content": "and seven wings.",
    "query_predicate_1": "only bloom for one day a year",
    "query_predicate_2": "have purple petals",
    "response_1": -99,
    "response_2": -99,
    "rt": 1236,
    "kind": "batozes",
    "predicate_1": "have six wings",
    "predicate_2": "have seven wings",
    "question_order": "same",
    "chapter": "Batozes",
    "quantifier": "generic"
   },
   {
    "trial_type": "critical",
    "page_type": "query",
    "condition": "uninterrupted",
    "chapter_num": 7,
    "page_num": 4,
    "page_content": "",
    "query_predicate_1": "have six wings",
    "query_predicate_2": "have seven wings",
    "response_1": 0.71,
    "response_2": 0.68,
    "rt": 7161,
    "kind": "batozes",
    "predicate_1": "have six wings",
    "predicate_2": "have seven wings",
    "question_order": "same",
    "chapter": "Batozes",
    "quantifier": "generic"
   },
   {
    "trial_type": "critical",
    "page_type": "text",
    "condition": "nme_uninterrupted",
    "chapter_num": 8,
    "page_num": 0,
    "page_content": "Reesles are strange, furry creatures, often found in the homes of the aliens. They are not house pets ",
    "query_predicate_1": "have six wings",
    "query_predicate_2": "have seven wings",
    "response_1": -99,
    "response_2": -99,
    "rt": 4163,
    "kind": "reesles",
    "predicate_1": "wear wutsats around their heads",
    "predicate_2": "wear krevnors around their heads",
    "question_order": "same",
    "chapter": "Reesles",
    "quantifier": "generic"
   },
   {
    "trial_type": "critical",
    "page_type": "text",
    "condition": "nme_uninterrupted",
    "chapter_num": 8,
    "page_num": 1,
    "page_content": "but quasi-domesticated animals. They will steal food from you if you are not paying attention. They have",
    "query_predicate_1": "have six wings",
    "query_predicate_2": "have seven wings",
    "response_1": -99,
    "response_2": -99,
    "rt": 5228,
    "kind": "reesles",
    "predicate_1": "wear wutsats around their heads",
    "predicate_2": "wear krevnors around their heads",
    "question_order": "same",
    "chapter": "Reesles",
    "quantifier": "generic"
   },
   {
    "trial_type": "critical",
    "page_type": "text",
    "condition": "nme_uninterrupted",
    "chapter_num": 8,
    "page_num": 2,
    "page_content": "special headgear to help other aliens identify their owners. Around their heads, they wear giant wutsats",
    "query_predicate_1": "have six wings",
    "query_predicate_2": "have seven wings",
    "response_1": -99,
    "response_2": -99,
    "rt": 6682,
    "kind": "reesles",
    "predicate_1": "wear wutsats around their heads",
    "predicate_2": "wear krevnors around their heads",
    "question_order": "same",
    "chapter": "Reesles",
    "quantifier": "generic"
   },
   {
    "trial_type": "critical",
    "page_type": "text",
    "condition": "nme_uninterrupted",
    "chapter_num": 8,
    "page_num": 3,
    "page_content": "and carry sticks with them.",
    "query_predicate_1": "have six wings",
    "query_predicate_2": "have seven wings",
    "response_1": -99,
    "response_2": -99,
    "rt": 2283,
    "kind": "reesles",
    "predicate_1": "wear wutsats around their heads",
    "predicate_2": "wear krevnors around their heads",
    "question_order": "same",
    "chapter": "Reesles",
    "quantifier": "generic"
   },
   {
    "trial_type": "critical",
    "page_type": "query",
    "condition": "nme_uninterrupted",
    "chapter_num": 8,
    "page_num": 4,
    "page_content": "",
    "query_predicate_1": "wear wutsats around their heads",
    "query_predicate_2": "carry sticks with them",
    "response_1": 0.89,
    "response_2": 0.77,
    "rt": 7293,
    "kind": "reesles",
    "predicate_1": "wear wutsats around their heads",
    "predicate_2": "wear krevnors around their heads",
    "question_order": "reverse",
    "chapter": "Reesles",
    "quantifier": "generic"
   },
   {
    "trial_type": "filler",
    "page_type": "text",
    "condition": "interrupted",
    "chapter_num": 9,
    "page_num": 0,
    "page_content": "Supools are the biggest creatures on Dax. They all live in the oceans and ",
    "query_predicate_1": "wear wutsats around their heads",
    "query_predicate_2": "carry sticks with them",
    "response_1": -99,
    "response_2": -99,
    "rt": 3270,
    "kind": "supools",
    "predicate_1": "live in the oceans",
    "predicate_2": "live for a very long time",
    "question_order": "reverse",
    "chapter": "Supools",
    "quantifier": "all"
   },
   {
    "trial_type": "filler",
    "page_type": "text",
    "condition": "interrupted",
    "chapter_num": 9,
    "page_num": 1,
    "page_content": "all of them live for a very long time. In the mornings, they like to play in the open ocean, and in the ",
    "query_predicate_1": "wear wutsats around their heads",
    "query_predicate_2": "carry sticks with them",
    "response_1": -99,
    "response_2": -99,
    "rt": 5603,
    "kind": "supools",
    "predicate_1": "live in the oceans",
    "predicate_2": "live for a very long time",
    "question_order": "reverse",
    "chapter": "Supools",
    "quantifier": "all"
   },
   {
    "trial_type": "filler",
    "page_type": "query",
    "condition": "interrupted",
    "chapter_num": 9,
    "page_num": -1,
    "page_content": "",
    "query_predicate_1": "live in the oceans",
    "query_predicate_2": "live for a very long time",
    "response_1": 0.97,
    "response_2": 0.95,
    "rt": 8077,
    "kind": "supools",
    "predicate_1": "live in the oceans",
    "predicate_2": "live for a very long time",
    "question_order": "reverse",
    "chapter": "Supools",
    "quantifier": "all"
   },
   {
    "trial_type": "filler",
    "page_type": "text",
    "condition": "interrupted",
    "chapter_num": 9,
    "page_num": 2,
    "page_content": "evenings, they come closer to the shore.",
    "query_predicate_1": "live in the oceans",
    "query_predicate_2": "live for a very long time",
    "response_1": 0.97,
    "response_2": 0.95,
    "rt": 2329,
    "kind": "supools",
    "predicate_1": "live in the oceans",
    "predicate_2": "live for a very long time",
    "question_order": "reverse",
    "chapter": "Supools",
    "quantifier": "all"
   },
   {
    "trial_type": "critical",
    "page_type": "text",
    "condition": "uninterrupted",
    "chapter_num": 10,
    "page_num": 0,
    "page_content": "Fengnors are smaller, nocturnal creatures. They often hide under the leaves of short trees to avoid ",
    "query_predicate_1": "live in the oceans",
    "query_predicate_2": "live for a very long time",
    "response_1": -99,
    "response_2": -99,
    "rt": 5315,
    "kind": "fengnor mated pairs",
    "predicate_1": "build nests in gluers",
    "predicate_2": "build nests in droops",
    "question_order": "reverse",
    "chapter": "Fengnors",
    "quantifier": "generic"
   },
   {
    "trial_type": "critical",
    "page_type": "text",
    "condition": "uninterrupted",
    "chapter_num": 10,
    "page_num": 1,
    "page_content": "being seen by larger predators. They scrape the bark off trees to eat. They have highly complex",
    "query_predicate_1": "live in the oceans",
    "query_predicate_2": "live for a very long time",
    "response_1": -99,
    "response_2": -99,
    "rt": 5399,
    "kind": "fengnor mated pairs",
    "predicate_1": "build nests in gluers",
    "predicate_2": "build nests in droops",
    "question_order": "reverse",
    "chapter": "Fengnors",
    "quantifier": "generic"
   },
   {
    "trial_type": "critical",
    "page_type": "text",
    "condition": "uninterrupted",
    "chapter_num": 10,
    "page_num": 2,
    "page_content": "mating habits. They mate for life, and the males often bring twigs and leaves to the females during",
    "query_predicate_1": "live in the oceans",
    "query_predicate_2": "live for a very long time",
    "response_1": -99,
    "response_2": -99,
    "rt": 5017,
    "kind": "fengnor mated pairs",
    "predicate_1": "build nests in gluers",
    "predicate_2": "build nests in droops",
    "question_order": "reverse",
    "chapter": "Fengnors",
    "quantifier": "generic"
   },
   {
    "trial_type": "critical",
    "page_type": "text",
    "condition": "uninterrupted",
    "chapter_num": 10,
    "page_num": 3,
    "page_content": "courtship. The mated pairs use these twigs and leaves to build their quite elaborate nests in gluers",
    "query_predicate_1": "live in the oceans",
    "query_predicate_2": "live for a very long time",
    "response_1": -99,
    "response_2": -99,
    "rt": 3977,
    "kind": "fengnor mated pairs",
    "predicate_1": "build nests in gluers",
    "predicate_2": "build nests in droops",
    "question_order": "reverse",
    "chapter": "Fengnors",
    "quantifier": "generic"
   },
   {
    "trial_type": "critical",
    "page_type": "text",
    "condition": "uninterrupted",
    "chapter_num": 10,
    "page_num": 4,
    "page_content": "and in droops.",
    "query_predicate_1": "live in the oceans",
    "query_predicate_2": "live for a very long time",
    "response_1": -99,
    "response_2": -99,
    "rt": 1598,
    "kind": "fengnor mated pairs",
    "predicate_1": "build nests in gluers",
    "predicate_2": "build nests in droops",
    "question_order": "reverse",
    "chapter": "Fengnors",
    "quantifier": "generic"
   },
   {
    "trial_type": "critical",
    "page_type": "query",
    "condition": "uninterrupted",
    "chapter_num": 10,
    "page_num": 5,
    "page_content": "",
    "query_predicate_1": "build nests in gluers",
    "query_predicate_2": "build nests in droops",
    "response_1": 0.98,
    "response_2": 0.97,
    "rt": 8190,
    "kind": "fengnor mated pairs",
    "predicate_1": "build nests in gluers",
    "predicate_2": "build nests in droops",
    "question_order": "reverse",
    "chapter": "Fengnors",
    "quantifier": "generic"
   },
   {
    "trial_type": "filler",
    "page_type": "text",
    "condition": "interrupted",
    "chapter_num": 11,
    "page_num": 0,
    "page_content": "Yomis are small, fast insect-like creatures. They all live in the ",
    "query_predicate_1": "build nests in gluers",
    "query_predicate_2": "build nests in droops",
    "response_1": -99,
    "response_2": -99,
    "rt": 5605,
    "kind": "yomis",
    "predicate_1": "live in the borderland woodlands",
    "predicate_2": "fly towards the mountains in search of food",
    "question_order": "reverse",
    "chapter": "Yomis",
    "quantifier": "all"
   },
   {
    "trial_type": "filler",
    "page_type": "text",
    "condition": "interrupted",
    "chapter_num": 11,
    "page_num": 1,
    "page_content": "borderland woodlands. They all fly towards the mountains in search of food, but they need to be careful ",
    "query_predicate_1": "build nests in gluers",
    "query_predicate_2": "build nests in droops",
    "response_1": -99,
    "response_2": -99,
    "rt": 5150,
    "kind": "yomis",
    "predicate_1": "live in the borderland woodlands",
    "predicate_2": "fly towards the mountains in search of food",
    "question_order": "reverse",
    "chapter": "Yomis",
    "quantifier": "all"
   },
   {
    "trial_type": "filler",
    "page_type": "query",
    "condition": "interrupted",
    "chapter_num": 11,
    "page_num": -1,
    "page_content": "",
    "query_predicate_1": "live in the borderland woodlands",
    "query_predicate_2": "fly towards the mountains in search of food",
    "response_1": 0.86,
    "response_2": 0.84,
    "rt": 7643,
    "kind": "yomis",
    "predicate_1": "live in the borderland woodlands",
    "predicate_2": "fly towards the mountains in search of food",
    "question_order": "same",
    "chapter": "Yomis",
    "quantifier": "all"
   },
   {
    "trial_type": "filler",
    "page_type": "text",
    "condition": "interrupted",
    "chapter_num": 11,
    "page_num": 2,
    "page_content": "of their natural predators, turmens.",
    "query_predicate_1": "live in the borderland woodlands",
    "query_predicate_2": "fly towards the mountains in search of food",
    "response_1": 0.86,
    "response_2": 0.84,
    "rt": 1809,
    "kind": "yomis",
    "predicate_1": "live in the borderland woodlands",
    "predicate_2": "fly towards the mountains in search of food",
    "question_order": "same",
    "chapter": "Yomis",
    "quantifier": "all"
   },
   {
    "trial_type": "filler",
    "page_type": "text",
    "condition": "uninterrupted",
    "chapter_num": 12,
    "page_num": 0,
    "page_content": "The morseth is an animal that lives part of its life in the sea and part of its life on land. Most morseths ",
    "query_predicate_1": "live in the borderland woodlands",
    "query_predicate_2": "fly towards the mountains in search of food",
    "response_1": -99,
    "response_2": -99,
    "rt": 5430,
    "kind": "morseths",
    "predicate_1": "build permanent structures called fendles",
    "predicate_2": "come on land to find mates",
    "question_order": "same",
    "chapter": "Morseths",
    "quantifier": "most"
   },
   {
    "trial_type": "filler",
    "page_type": "text",
    "condition": "uninterrupted",
    "chapter_num": 12,
    "page_num": 1,
    "page_content": "come on land to find mates and to bury their dead. Most morseths build permanent structures called fendles in order to bury their dead ",
    "query_predicate_1": "live in the borderland woodlands",
    "query_predicate_2": "fly towards the mountains in search of food",
    "response_1": -99,
    "response_2": -99,
    "rt": 5833,
    "kind": "morseths",
    "predicate_1": "build permanent structures called fendles",
    "predicate_2": "come on land to find mates",
    "question_order": "same",
    "chapter": "Morseths",
    "quantifier": "most"
   },
   {
    "trial_type": "filler",
    "page_type": "text",
    "condition": "uninterrupted",
    "chapter_num": 12,
    "page_num": 2,
    "page_content": "kin, and fendles are usually made out of wood.",
    "query_predicate_1": "live in the borderland woodlands",
    "query_predicate_2": "fly towards the mountains in search of food",
    "response_1": -99,
    "response_2": -99,
    "rt": 3028,
    "kind": "morseths",
    "predicate_1": "build permanent structures called fendles",
    "predicate_2": "come on land to find mates",
    "question_order": "same",
    "chapter": "Morseths",
    "quantifier": "most"
   },
   {
    "trial_type": "filler",
    "page_type": "query",
    "condition": "uninterrupted",
    "chapter_num": 12,
    "page_num": 3,
    "page_content": "",
    "query_predicate_1": "build permanent structures called fendles",
    "query_predicate_2": "come on land to find mates",
    "response_1": 0.84,
    "response_2": 0.87,
    "rt": 7375,
    "kind": "morseths",
    "predicate_1": "build permanent structures called fendles",
    "predicate_2": "come on land to find mates",
    "question_order": "reverse",
    "chapter": "Morseths",
    "quantifier": "most"
   },
   {
    "trial_type": "critical",
    "page_type": "text",
    "condition": "uninterrupted",
    "chapter_num": 13,
    "page_num": 0,
    "page_content": "Mooks are ferocious creatures that live on the continent of Benli. Benli has dramatic elevation changes ",
    "query_predicate_1": "build permanent structures called fendles",
    "query_predicate_2": "come on land to find mates",
    "response_1": -99,
    "response_2": -99,
    "rt": 4315,
    "kind": "mooks",
    "predicate_1": "have territories at the tops of tall mountains",
    "predicate_2": "have territories at the bottom of deep canyons",
    "question_order": "reverse",
    "chapter": "Mooks",
    "quantifier": "generic"
   },
   {
    "trial_type": "critical",
    "page_type": "text",
    "condition": "uninterrupted",
    "chapter_num": 13,
    "page_num": 1,
    "page_content": "unlike any other continent on Dax. Animals find terrority in locations that will maximize their chances ",
    "query_predicate_1": "build permanent structures called fendles",
    "query_predicate_2": "come on land to find mates",
    "response_1": -99,
    "response_2": -99,
    "rt": 4260,
    "kind": "mooks",
    "predicate_1": "have territories at the tops of tall mountains",
    "predicate_2": "have territories at the bottom of deep canyons",
    "question_order": "reverse",
    "chapter": "Mooks",
    "quantifier": "generic"
   },
   {
    "trial_type": "critical",
    "page_type": "text",
    "condition": "uninterrupted",
    "chapter_num": 13,
    "page_num": 2,
    "page_content": "of survival. Mooks have territories at the tops of tall mountains",
    "query_predicate_1": "build permanent structures called fendles",
    "query_predicate_2": "come on land to find mates",
    "response_1": -99,
    "response_2": -99,
    "rt": 2640,
    "kind": "mooks",
    "predicate_1": "have territories at the tops of tall mountains",
    "predicate_2": "have territories at the bottom of deep canyons",
    "question_order": "reverse",
    "chapter": "Mooks",
    "quantifier": "generic"
   },
   {
    "trial_type": "critical",
    "page_type": "text",
    "condition": "uninterrupted",
    "chapter_num": 13,
    "page_num": 3,
    "page_content": "and at the bottom of deep canyons.",
    "query_predicate_1": "build permanent structures called fendles",
    "query_predicate_2": "come on land to find mates",
    "response_1": -99,
    "response_2": -99,
    "rt": 1675,
    "kind": "mooks",
    "predicate_1": "have territories at the tops of tall mountains",
    "predicate_2": "have territories at the bottom of deep canyons",
    "question_order": "reverse",
    "chapter": "Mooks",
    "quantifier": "generic"
   },
   {
    "trial_type": "critical",
    "page_type": "query",
    "condition": "uninterrupted",
    "chapter_num": 13,
    "page_num": 4,
    "page_content": "",
    "query_predicate_1": "have territories at the tops of tall mountains",
    "query_predicate_2": "have territories at the bottom of deep canyons",
    "response_1": 0.8,
    "response_2": 0.84,
    "rt": 13416,
    "kind": "mooks",
    "predicate_1": "have territories at the tops of tall mountains",
    "predicate_2": "have territories at the bottom of deep canyons",
    "question_order": "same",
    "chapter": "Mooks",
    "quantifier": "generic"
   },
   {
    "trial_type": "critical",
    "page_type": "text",
    "condition": "nme_interrupted",
    "chapter_num": 14,
    "page_num": 0,
    "page_content": "The aliens have many different kinds of specialized skills and trades, such as basket weaving. Crafters are found all over Dax, but ",
    "query_predicate_1": "have territories at the tops of tall mountains",
    "query_predicate_2": "have territories at the bottom of deep canyons",
    "response_1": -99,
    "response_2": -99,
    "rt": 7323,
    "kind": "basket weavers",
    "predicate_1": "are part of the Tinno guild",
    "predicate_2": "are part of the Farza guild",
    "question_order": "same",
    "chapter": "Crafts",
    "quantifier": "generic"
   },
   {
    "trial_type": "critical",
    "page_type": "text",
    "condition": "nme_interrupted",
    "chapter_num": 14,
    "page_num": 1,
    "page_content": "they are especially common in the city of Rondoo, where aliens from all over go to buy luxury goods. To ",
    "query_predicate_1": "have territories at the tops of tall mountains",
    "query_predicate_2": "have territories at the bottom of deep canyons",
    "response_1": -99,
    "response_2": -99,
    "rt": 9794,
    "kind": "basket weavers",
    "predicate_1": "are part of the Tinno guild",
    "predicate_2": "are part of the Farza guild",
    "question_order": "same",
    "chapter": "Crafts",
    "quantifier": "generic"
   },
   {
    "trial_type": "critical",
    "page_type": "text",
    "condition": "nme_interrupted",
    "chapter_num": 14,
    "page_num": 2,
    "page_content": "help make themselves known, crafters join guilds with other crafters of the same trade. Basket weavers are part of the Tinno guild ",
    "query_predicate_1": "have territories at the tops of tall mountains",
    "query_predicate_2": "have territories at the bottom of deep canyons",
    "response_1": -99,
    "response_2": -99,
    "rt": 5371,
    "kind": "basket weavers",
    "predicate_1": "are part of the Tinno guild",
    "predicate_2": "are part of the Farza guild",
    "question_order": "same",
    "chapter": "Crafts",
    "quantifier": "generic"
   },
   {
    "trial_type": "critical",
    "page_type": "query",
    "condition": "nme_interrupted",
    "chapter_num": 14,
    "page_num": -1,
    "page_content": "",
    "query_predicate_1": "are part of the Tinno guild",
    "query_predicate_2": "sell their baskets in the Warfi marketplace",
    "response_1": 0.76,
    "response_2": 0.85,
    "rt": 7893,
    "kind": "basket weavers",
    "predicate_1": "are part of the Tinno guild",
    "predicate_2": "are part of the Farza guild",
    "question_order": "same",
    "chapter": "Crafts",
    "quantifier": "generic"
   },
   {
    "trial_type": "critical",
    "page_type": "text",
    "condition": "nme_interrupted",
    "chapter_num": 14,
    "page_num": 3,
    "page_content": "and pledge allegiance to Tinnius the Elder.",
    "query_predicate_1": "are part of the Tinno guild",
    "query_predicate_2": "sell their baskets in the Warfi marketplace",
    "response_1": 0.76,
    "response_2": 0.85,
    "rt": 1426,
    "kind": "basket weavers",
    "predicate_1": "are part of the Tinno guild",
    "predicate_2": "are part of the Farza guild",
    "question_order": "same",
    "chapter": "Crafts",
    "quantifier": "generic"
   },
   {
    "trial_type": "critical",
    "page_type": "text",
    "condition": "interrupted",
    "chapter_num": 15,
    "page_num": 0,
    "page_content": "Vimbles are social insects that live in colonies of up to a thousand individuals. Vimbles live for a year ",
    "query_predicate_1": "are part of the Tinno guild",
    "query_predicate_2": "sell their baskets in the Warfi marketplace",
    "response_1": -99,
    "response_2": -99,
    "rt": 5010,
    "kind": "vimble queens",
    "predicate_1": "hibernate in fallen logs",
    "predicate_2": "hibernate in the abandoned burrows of other animals",
    "question_order": "same",
    "chapter": "Vimbles",
    "quantifier": "generic"
   },
   {
    "trial_type": "critical",
    "page_type": "text",
    "condition": "interrupted",
    "chapter_num": 15,
    "page_num": 1,
    "page_content": "or less. They have a single queen, who must find somewhere to hibernate over the winter before ",
    "query_predicate_1": "are part of the Tinno guild",
    "query_predicate_2": "sell their baskets in the Warfi marketplace",
    "response_1": -99,
    "response_2": -99,
    "rt": 5507,
    "kind": "vimble queens",
    "predicate_1": "hibernate in fallen logs",
    "predicate_2": "hibernate in the abandoned burrows of other animals",
    "question_order": "same",
    "chapter": "Vimbles",
    "quantifier": "generic"
   },
   {
    "trial_type": "critical",
    "page_type": "text",
    "condition": "interrupted",
    "chapter_num": 15,
    "page_num": 2,
    "page_content": "starting a new colony. Vimble queens hibernate in fallen logs  ",
    "query_predicate_1": "are part of the Tinno guild",
    "query_predicate_2": "sell their baskets in the Warfi marketplace",
    "response_1": -99,
    "response_2": -99,
    "rt": 3081,
    "kind": "vimble queens",
    "predicate_1": "hibernate in fallen logs",
    "predicate_2": "hibernate in the abandoned burrows of other animals",
    "question_order": "same",
    "chapter": "Vimbles",
    "quantifier": "generic"
   },
   {
    "trial_type": "critical",
    "page_type": "query",
    "condition": "interrupted",
    "chapter_num": 15,
    "page_num": -1,
    "page_content": "",
    "query_predicate_1": "hibernate in fallen logs",
    "query_predicate_2": "hibernate in the abandoned burrows of other animals",
    "response_1": 0.88,
    "response_2": 0.77,
    "rt": 6212,
    "kind": "vimble queens",
    "predicate_1": "hibernate in fallen logs",
    "predicate_2": "hibernate in the abandoned burrows of other animals",
    "question_order": "same",
    "chapter": "Vimbles",
    "quantifier": "generic"
   },
   {
    "trial_type": "critical",
    "page_type": "text",
    "condition": "interrupted",
    "chapter_num": 15,
    "page_num": 3,
    "page_content": "and only emerge when the weather has become warmer.",
    "query_predicate_1": "hibernate in fallen logs",
    "query_predicate_2": "hibernate in the abandoned burrows of other animals",
    "response_1": 0.88,
    "response_2": 0.77,
    "rt": 2139,
    "kind": "vimble queens",
    "predicate_1": "hibernate in fallen logs",
    "predicate_2": "hibernate in the abandoned burrows of other animals",
    "question_order": "same",
    "chapter": "Vimbles",
    "quantifier": "generic"
   },
   {
    "trial_type": "filler",
    "page_type": "text",
    "condition": "uninterrupted",
    "chapter_num": 16,
    "page_num": 0,
    "page_content": "Kazzes are a kind of plant that grow all over Dax. They produce fruit in the springtime, but the",
    "query_predicate_1": "hibernate in fallen logs",
    "query_predicate_2": "hibernate in the abandoned burrows of other animals",
    "response_1": -99,
    "response_2": -99,
    "rt": 4685,
    "kind": "feps",
    "predicate_1": "eat kazzes",
    "predicate_2": "come close to kazzes",
    "question_order": "same",
    "chapter": "Kazzes",
    "quantifier": "none"
   },
   {
    "trial_type": "filler",
    "page_type": "text",
    "condition": "uninterrupted",
    "chapter_num": 16,
    "page_num": 1,
    "page_content": " fruit is poisonous to animals. No feps eat kazzes nor do they come close. Kazzes can be highly toxic ",
    "query_predicate_1": "hibernate in fallen logs",
    "query_predicate_2": "hibernate in the abandoned burrows of other animals",
    "response_1": -99,
    "response_2": -99,
    "rt": 5909,
    "kind": "feps",
    "predicate_1": "eat kazzes",
    "predicate_2": "come close to kazzes",
    "question_order": "same",
    "chapter": "Kazzes",
    "quantifier": "none"
   },
   {
    "trial_type": "filler",
    "page_type": "text",
    "condition": "uninterrupted",
    "chapter_num": 16,
    "page_num": 2,
    "page_content": "and this poison is a defensive mechanism for kazzes.",
    "query_predicate_1": "hibernate in fallen logs",
    "query_predicate_2": "hibernate in the abandoned burrows of other animals",
    "response_1": -99,
    "response_2": -99,
    "rt": 3072,
    "kind": "feps",
    "predicate_1": "eat kazzes",
    "predicate_2": "come close to kazzes",
    "question_order": "same",
    "chapter": "Kazzes",
    "quantifier": "none"
   },
   {
    "trial_type": "filler",
    "page_type": "query",
    "condition": "uninterrupted",
    "chapter_num": 16,
    "page_num": 3,
    "page_content": "",
    "query_predicate_1": "eat kazzes",
    "query_predicate_2": "come close to kazzes",
    "response_1": 0.78,
    "response_2": 0.87,
    "rt": 5788,
    "kind": "feps",
    "predicate_1": "eat kazzes",
    "predicate_2": "come close to kazzes",
    "question_order": "same",
    "chapter": "Kazzes",
    "quantifier": "none"
   },
   {
    "trial_type": "critical",
    "page_type": "text",
    "condition": "interrupted",
    "chapter_num": 17,
    "page_num": 0,
    "page_content": "Kweps hunt in packs. Even though they are pack animals, all of them have highly idiosyncractic food ",
    "query_predicate_1": "eat kazzes",
    "query_predicate_2": "come close to kazzes",
    "response_1": -99,
    "response_2": -99,
    "rt": 4999,
    "kind": "kweps",
    "predicate_1": "chew on xorfun",
    "predicate_2": "chew on tunkel",
    "question_order": "same",
    "chapter": "Kweps",
    "quantifier": "generic"
   },
   {
    "trial_type": "critical",
    "page_type": "text",
    "condition": "interrupted",
    "chapter_num": 17,
    "page_num": 1,
    "page_content": "preferences and behaviors. Some of them like to eat apples and others like to eat oranges. When they go ",
    "query_predicate_1": "eat kazzes",
    "query_predicate_2": "come close to kazzes",
    "response_1": -99,
    "response_2": -99,
    "rt": 4633,
    "kind": "kweps",
    "predicate_1": "chew on xorfun",
    "predicate_2": "chew on tunkel",
    "question_order": "same",
    "chapter": "Kweps",
    "quantifier": "generic"
   },
   {
    "trial_type": "critical",
    "page_type": "text",
    "condition": "interrupted",
    "chapter_num": 17,
    "page_num": 2,
    "page_content": "hunting at night they look for creatures sleeping alone, not in groups. Right before they go hunting, the kweps chew on xorfun",
    "query_predicate_1": "eat kazzes",
    "query_predicate_2": "come close to kazzes",
    "response_1": -99,
    "response_2": -99,
    "rt": 6104,
    "kind": "kweps",
    "predicate_1": "chew on xorfun",
    "predicate_2": "chew on tunkel",
    "question_order": "same",
    "chapter": "Kweps",
    "quantifier": "generic"
   },
   {
    "trial_type": "critical",
    "page_type": "query",
    "condition": "interrupted",
    "chapter_num": 17,
    "page_num": -1,
    "page_content": "",
    "query_predicate_1": "chew on xorfun",
    "query_predicate_2": "chew on tunkel",
    "response_1": 0.86,
    "response_2": 0.83,
    "rt": 6616,
    "kind": "kweps",
    "predicate_1": "chew on xorfun",
    "predicate_2": "chew on tunkel",
    "question_order": "reverse",
    "chapter": "Kweps",
    "quantifier": "generic"
   },
   {
    "trial_type": "critical",
    "page_type": "text",
    "condition": "interrupted",
    "chapter_num": 17,
    "page_num": 3,
    "page_content": "and howl towards the sky.",
    "query_predicate_1": "chew on xorfun",
    "query_predicate_2": "chew on tunkel",
    "response_1": 0.86,
    "response_2": 0.83,
    "rt": 1320,
    "kind": "kweps",
    "predicate_1": "chew on xorfun",
    "predicate_2": "chew on tunkel",
    "question_order": "reverse",
    "chapter": "Kweps",
    "quantifier": "generic"
   },
   {
    "trial_type": "critical",
    "page_type": "text",
    "condition": "nme_uninterrupted",
    "chapter_num": 18,
    "page_num": 0,
    "page_content": "Isooms are tree-like plants that are found in hilly regions of Fale. Their fruit is edible, and the aliens often ",
    "query_predicate_1": "chew on xorfun",
    "query_predicate_2": "chew on tunkel",
    "response_1": -99,
    "response_2": -99,
    "rt": 5080,
    "kind": "isooms",
    "predicate_1": "produce fruit with bumpy skin",
    "predicate_2": "produce fruit with smooth skin",
    "question_order": "reverse",
    "chapter": "Isooms",
    "quantifier": "generic"
   },
   {
    "trial_type": "critical",
    "page_type": "text",
    "condition": "nme_uninterrupted",
    "chapter_num": 18,
    "page_num": 1,
    "page_content": "cultivate isooms for food. Isooms produce fruit with bumpy skin ",
    "query_predicate_1": "chew on xorfun",
    "query_predicate_2": "chew on tunkel",
    "response_1": -99,
    "response_2": -99,
    "rt": 2565,
    "kind": "isooms",
    "predicate_1": "produce fruit with bumpy skin",
    "predicate_2": "produce fruit with smooth skin",
    "question_order": "reverse",
    "chapter": "Isooms",
    "quantifier": "generic"
   },
   {
    "trial_type": "critical",
    "page_type": "text",
    "condition": "nme_uninterrupted",
    "chapter_num": 18,
    "page_num": 2,
    "page_content": "and a sour taste.",
    "query_predicate_1": "chew on xorfun",
    "query_predicate_2": "chew on tunkel",
    "response_1": -99,
    "response_2": -99,
    "rt": 1286,
    "kind": "isooms",
    "predicate_1": "produce fruit with bumpy skin",
    "predicate_2": "produce fruit with smooth skin",
    "question_order": "reverse",
    "chapter": "Isooms",
    "quantifier": "generic"
   },
   {
    "trial_type": "critical",
    "page_type": "query",
    "condition": "nme_uninterrupted",
    "chapter_num": 18,
    "page_num": 3,
    "page_content": "",
    "query_predicate_1": "produce fruit with bumpy skin",
    "query_predicate_2": "produce fruit with a sour taste",
    "response_1": 0.8,
    "response_2": 0.85,
    "rt": 8236,
    "kind": "isooms",
    "predicate_1": "produce fruit with bumpy skin",
    "predicate_2": "produce fruit with smooth skin",
    "question_order": "reverse",
    "chapter": "Isooms",
    "quantifier": "generic"
   },
   {
    "trial_type": "critical",
    "page_type": "text",
    "condition": "interrupted",
    "chapter_num": 19,
    "page_num": 0,
    "page_content": "Krens are a tribe of the aliens that live on the continent of Benli, which has no agriculture. Like most ",
    "query_predicate_1": "produce fruit with bumpy skin",
    "query_predicate_2": "produce fruit with a sour taste",
    "response_1": -99,
    "response_2": -99,
    "rt": 4024,
    "kind": "Krens",
    "predicate_1": "are stup-herders",
    "predicate_2": "are fishermen",
    "question_order": "reverse",
    "chapter": "Finding food",
    "quantifier": "generic"
   },
   {
    "trial_type": "critical",
    "page_type": "text",
    "condition": "interrupted",
    "chapter_num": 19,
    "page_num": 1,
    "page_content": "creatures on Dax, Krens eat other creatures to survive. Animals like stups, four-legged creatures with ",
    "query_predicate_1": "produce fruit with bumpy skin",
    "query_predicate_2": "produce fruit with a sour taste",
    "response_1": -99,
    "response_2": -99,
    "rt": 5870,
    "kind": "Krens",
    "predicate_1": "are stup-herders",
    "predicate_2": "are fishermen",
    "question_order": "reverse",
    "chapter": "Finding food",
    "quantifier": "generic"
   },
   {
    "trial_type": "critical",
    "page_type": "text",
    "condition": "interrupted",
    "chapter_num": 19,
    "page_num": 2,
    "page_content": "large antlers, are a resource for the Krens. Stups roam all over the windy highlands of Benli, far from the oceans. Krens are stup-herders",
    "query_predicate_1": "produce fruit with bumpy skin",
    "query_predicate_2": "produce fruit with a sour taste",
    "response_1": -99,
    "response_2": -99,
    "rt": 8016,
    "kind": "Krens",
    "predicate_1": "are stup-herders",
    "predicate_2": "are fishermen",
    "question_order": "reverse",
    "chapter": "Finding food",
    "quantifier": "generic"
   },
   {
    "trial_type": "critical",
    "page_type": "query",
    "condition": "interrupted",
    "chapter_num": 19,
    "page_num": -1,
    "page_content": "",
    "query_predicate_1": "are stup-herders",
    "query_predicate_2": "are fishermen",
    "response_1": 0.84,
    "response_2": 0.78,
    "rt": 8646,
    "kind": "Krens",
    "predicate_1": "are stup-herders",
    "predicate_2": "are fishermen",
    "question_order": "same",
    "chapter": "Finding food",
    "quantifier": "generic"
   },
   {
    "trial_type": "critical",
    "page_type": "text",
    "condition": "interrupted",
    "chapter_num": 19,
    "page_num": 3,
    "page_content": "and incorporate stups into their religion.",
    "query_predicate_1": "are stup-herders",
    "query_predicate_2": "are fishermen",
    "response_1": 0.84,
    "response_2": 0.78,
    "rt": 2449,
    "kind": "Krens",
    "predicate_1": "are stup-herders",
    "predicate_2": "are fishermen",
    "question_order": "same",
    "chapter": "Finding food",
    "quantifier": "generic"
   },
   {
    "trial_type": "filler",
    "page_type": "text",
    "condition": "uninterrupted",
    "chapter_num": 20,
    "page_num": 0,
    "page_content": "Plovs travel in herds and are very territorial. They used to live in the continent of Aga, but in recent",
    "query_predicate_1": "are stup-herders",
    "query_predicate_2": "are fishermen",
    "response_1": -99,
    "response_2": -99,
    "rt": 8303,
    "kind": "plovs",
    "predicate_1": "live in the continent of Aga",
    "predicate_2": "are attacked by other creatures",
    "question_order": "same",
    "chapter": "Plovs",
    "quantifier": "none"
   },
   {
    "trial_type": "filler",
    "page_type": "text",
    "condition": "uninterrupted",
    "chapter_num": 20,
    "page_num": 1,
    "page_content": "years they all have migrated to the continent Caro. When they migrated to Caro, they intruded upon the territory of other ",
    "query_predicate_1": "are stup-herders",
    "query_predicate_2": "are fishermen",
    "response_1": -99,
    "response_2": -99,
    "rt": 9734,
    "kind": "plovs",
    "predicate_1": "live in the continent of Aga",
    "predicate_2": "are attacked by other creatures",
    "question_order": "same",
    "chapter": "Plovs",
    "quantifier": "none"
   },
   {
    "trial_type": "filler",
    "page_type": "text",
    "condition": "uninterrupted",
    "chapter_num": 20,
    "page_num": 2,
    "page_content": "creatures and struggled to find a new home. Now that they have their own territory, they are never attacked by other creatures and ",
    "query_predicate_1": "are stup-herders",
    "query_predicate_2": "are fishermen",
    "response_1": -99,
    "response_2": -99,
    "rt": 12396,
    "kind": "plovs",
    "predicate_1": "live in the continent of Aga",
    "predicate_2": "are attacked by other creatures",
    "question_order": "same",
    "chapter": "Plovs",
    "quantifier": "none"
   },
   {
    "trial_type": "filler",
    "page_type": "text",
    "condition": "uninterrupted",
    "chapter_num": 20,
    "page_num": 3,
    "page_content": "they live quite happily near the water.",
    "query_predicate_1": "are stup-herders",
    "query_predicate_2": "are fishermen",
    "response_1": -99,
    "response_2": -99,
    "rt": 1872,
    "kind": "plovs",
    "predicate_1": "live in the continent of Aga",
    "predicate_2": "are attacked by other creatures",
    "question_order": "same",
    "chapter": "Plovs",
    "quantifier": "none"
   },
   {
    "trial_type": "filler",
    "page_type": "query",
    "condition": "uninterrupted",
    "chapter_num": 20,
    "page_num": 4,
    "page_content": "",
    "query_predicate_1": "live in the continent of Aga",
    "query_predicate_2": "are attacked by other creatures",
    "response_1": 0.84,
    "response_2": 0.9,
    "rt": 6849,
    "kind": "plovs",
    "predicate_1": "live in the continent of Aga",
    "predicate_2": "are attacked by other creatures",
    "question_order": "same",
    "chapter": "Plovs",
    "quantifier": "none"
   }
  ],
  "catch_trials": [
   {
    "condition": "practice",
    "check_index": 1,
    "property": "dogs bark",
    "tested_on": -1,
    "response": 0.99,
    "correct": true
   },
   {
    "condition": "practice",
    "check_index": 2,
    "property": "birds are male",
    "tested_on": -1,
    "response": 0.49,
    "correct": true
   },
   {
    "condition": "practice",
    "check_index": 2,
    "property": "cats get cancer",
    "tested_on": -1,
    "response": 0.36,
    "correct": true
   },
   {
    "condition": "practice",
    "check_index": 2,
    "property": "lions lay eggs",
    "tested_on": -1,
    "response": 0,
    "correct": true
   },
   {
    "condition": "memory_check",
    "check_index": 0,
    "property": "cranoor is the king of all beings",
    "tested_on": 0,
    "response": 0,
    "correct": 1
   },
   {
    "condition": "memory_check",
    "check_index": 1,
    "property": "no plovs live in the continent of Aga",
    "tested_on": 1,
    "response": 0,
    "correct": 0
   },
   {
    "condition": "memory_check",
    "check_index": 2,
    "property": "most morseths build permanent structures called fendles",
    "tested_on": 1,
    "response": 1,
    "correct": 1
   },
   {
    "condition": "memory_check",
    "check_index": 3,
    "property": "taifles have gold spots that are sticky",
    "tested_on": 0,
    "response": 0,
    "correct": 1
   },
   {
    "condition": "memory_check",
    "check_index": 4,
    "property": "lorches have long legs and breathe underwater",
    "tested_on": 0,
    "response": 0,
    "correct": 1
   },
   {
    "condition": "memory_check",
    "check_index": 5,
    "property": "dorbs have infected, yellow scales ",
    "tested_on": 0,
    "response": 1,
    "correct": 0
   },
   {
    "condition": "memory_check",
    "check_index": 6,
    "property": "all supools live in the oceans",
    "tested_on": 1,
    "response": 0,
    "correct": 0
   },
   {
    "condition": "memory_check",
    "check_index": 7,
    "property": "all yomis live in the borderland woodlands",
    "tested_on": 1,
    "response": 0,
    "correct": 0
   },
   {
    "condition": "memory_check",
    "check_index": 8,
    "property": "no kweps eat plants",
    "tested_on": 0,
    "response": 0,
    "correct": 1
   },
   {
    "condition": "memory_check",
    "check_index": 9,
    "property": "most lodeks only bloom for one day a year",
    "tested_on": 1,
    "response": 0,
    "correct": 0
   },
   {
    "condition": "explanation",
    "check_index": -1,
    "property": "i tried to go on the info provided and base my views off of that and give a best guest type anwser",
    "tested_on": -1,
    "response": -1,
    "correct": -1
   }
  ],
  "system": {
   "Browser": "Chrome",
   "OS": "Windows",
   "screenH": 1080,
   "screenW": 1920
  },
  "subject_information": {
   "language": "United States",
   "enjoyment": "1",
   "asses": "Yes",
   "age": "32",
   "gender": "",
   "education": "3",
   "problems": "no",
   "fairprice": "2.00",
   "comments": ""
  },
  "time_in_minutes": 9.939566666666666
 }
}