{
 "AssignmentId": "3LS2AMNW5GE90ONVW19ZB8EUJOKQO2",
 "WorkerId": "a0ec94db1fda5c197a78f5a153474ded",
 "HITId": "3QMELQS6Y5ZG0ZYYJI73BE6K3EE6RF",
 "AssignmentStatus": "Approved",
 "AutoApprovalTime": "2020-03-21T14:47:37.000Z",
 "AcceptTime": "2020-03-20T14:31:06.000Z",
 "SubmitTime": "2020-03-20T14:47:37.000Z",
 "ApprovalTime": "2020-03-21T14:47:48.000Z",
 "answers": {
  "trials": [
   {
    "trial_type": "filler",
    "page_type": "text",
    "condition": "uninterrupted",
    "chapter_num": 0,
    "page_num": 0,
    "page_content": "Dax is a lot like Earth.  Like Earth it has seven continents, in similar locations, but instead of North ",
    "response_1": -99,
    "rt": 25739,
    "kind": "NA",
    "predicate_1": "NA",
    "question_order": "NA",
    "chapter": "An introduction to Dax",
    "quantifier": "generic"
   },
   {
    "trial_type": "filler",
    "page_type": "text",
    "condition": "uninterrupted",
    "chapter_num": 0,
    "page_num": 1,
    "page_content": " America, South America, Africa, Europe, Asia, Australia, and Antarctica, the continents are  ",
    "response_1": -99,
    "rt": 7109,
    "kind": "NA",
    "predicate_1": "NA",
    "question_order": "NA",
    "chapter": "An introduction to Dax",
    "quantifier": "generic"
   },
   {
    "trial_type": "filler",
    "page_type": "text",
    "condition": "uninterrupted",
    "chapter_num": 0,
    "page_num": 2,
    "page_content": " called  Aga,  Benli, Caro, Dodi, Ente, Fale, and Gomi. Its climate is a lot like Earth's, too. But the",
    "response_1": -99,
    "rt": 7762,
    "kind": "NA",
    "predicate_1": "NA",
    "question_order": "NA",
    "chapter": "An introduction to Dax",
    "quantifier": "generic"
   },
   {
    "trial_type": "filler",
    "page_type": "text",
    "condition": "uninterrupted",
    "chapter_num": 0,
    "page_num": 3,
    "page_content": "  plants and animals of Dax are quite different.",
    "response_1": -99,
    "rt": 5006,
    "kind": "NA",
    "predicate_1": "NA",
    "question_order": "NA",
    "chapter": "An introduction to Dax",
    "quantifier": "generic"
   },
   {
    "trial_type": "filler",
    "page_type": "text",
    "condition": "uninterrupted",
    "chapter_num": 1,
    "page_num": 0,
    "page_content": "Nannus only feed on rare flowers called lodeks. Most lodeks only ",
    "response_1": -99,
    "rt": 5569,
    "kind": "lodeks",
    "predicate_1": "only bloom for one day a year",
    "question_order": "NA",
    "chapter": "Nannus",
    "quantifier": "most"
   },
   {
    "trial_type": "filler",
    "page_type": "text",
    "condition": "uninterrupted",
    "chapter_num": 1,
    "page_num": 1,
    "page_content": "bloom for one day a year, and most have purple petals. The plant that ",
    "response_1": -99,
    "rt": 5085,
    "kind": "lodeks",
    "predicate_1": "only bloom for one day a year",
    "question_order": "NA",
    "chapter": "Nannus",
    "quantifier": "most"
   },
   {
    "trial_type": "filler",
    "page_type": "text",
    "condition": "uninterrupted",
    "chapter_num": 1,
    "page_num": 2,
    "page_content": "lodeks grow on is hard to find because it only grows next to caves.",
    "response_1": -99,
    "rt": 3589,
    "kind": "lodeks",
    "predicate_1": "only bloom for one day a year",
    "question_order": "NA",
    "chapter": "Nannus",
    "quantifier": "most"
   },
   {
    "trial_type": "filler",
    "page_type": "query",
    "condition": "uninterrupted",
    "chapter_num": 1,
    "page_num": 3,
    "page_content": "",
    "query_predicate_1": "only bloom for one day a year",
    "response_1": 0.98,
    "rt": 34674,
    "kind": "lodeks",
    "predicate_1": "only bloom for one day a year",
    "question_order": "NA",
    "chapter": "Nannus",
    "quantifier": "most"
   },
   {
    "trial_type": "filler",
    "page_type": "text",
    "condition": "uninterrupted",
    "chapter_num": 2,
    "page_num": 0,
    "page_content": "Wopis are extremely rare creatures. They only live in the desert and ",
    "query_predicate_1": "only bloom for one day a year",
    "response_1": -99,
    "rt": 7402,
    "kind": "wopis",
    "predicate_1": "live in the desert",
    "question_order": "NA",
    "chapter": "Wopis",
    "quantifier": "all"
   },
   {
    "trial_type": "filler",
    "page_type": "text",
    "condition": "uninterrupted",
    "chapter_num": 2,
    "page_num": 1,
    "page_content": "they all are very hard to find. Wopis sleep during the day to avoid ",
    "query_predicate_1": "only bloom for one day a year",
    "response_1": -99,
    "rt": 3274,
    "kind": "wopis",
    "predicate_1": "live in the desert",
    "question_order": "NA",
    "chapter": "Wopis",
    "quantifier": "all"
   },
   {
    "trial_type": "filler",
    "page_type": "text",
    "condition": "uninterrupted",
    "chapter_num": 2,
    "page_num": 2,
    "page_content": "the heat, and look for food at night when it's cool.",
    "query_predicate_1": "only bloom for one day a year",
    "response_1": -99,
    "rt": 3409,
    "kind": "wopis",
    "predicate_1": "live in the desert",
    "question_order": "NA",
    "chapter": "Wopis",
    "quantifier": "all"
   },
   {
    "trial_type": "filler",
    "page_type": "query",
    "condition": "uninterrupted",
    "chapter_num": 2,
    "page_num": 3,
    "page_content": "",
    "query_predicate_1": "live in the desert",
    "response_1": 1,
    "rt": 13782,
    "kind": "wopis",
    "predicate_1": "live in the desert",
    "question_order": "NA",
    "chapter": "Wopis",
    "quantifier": "all"
   },
   {
    "trial_type": "critical",
    "page_type": "text",
    "condition": "interrupted",
    "chapter_num": 3,
    "page_num": 0,
    "page_content": "Glippets are large creatures, quite intelligent, with a life-span of about ",
    "query_predicate_1": "live in the desert",
    "response_1": -99,
    "rt": 5535,
    "kind": "glippets",
    "predicate_1": "live on the continent of Caro",
    "question_order": "NA",
    "chapter": "Glippets",
    "quantifier": "generic"
   },
   {
    "trial_type": "critical",
    "page_type": "text",
    "condition": "interrupted",
    "chapter_num": 3,
    "page_num": 1,
    "page_content": "sixty years. They live on the southern continent of Caro",
    "query_predicate_1": "live in the desert",
    "response_1": -99,
    "rt": 2678,
    "kind": "glippets",
    "predicate_1": "live on the continent of Caro",
    "question_order": "NA",
    "chapter": "Glippets",
    "quantifier": "generic"
   },
   {
    "trial_type": "critical",
    "page_type": "query",
    "condition": "interrupted",
    "chapter_num": 3,
    "page_num": -1,
    "page_content": "",
    "query_predicate_1": "live on the continent of Caro",
    "response_1": 1,
    "rt": 14535,
    "kind": "glippets",
    "predicate_1": "live on the continent of Caro",
    "question_order": "NA",
    "chapter": "Glippets",
    "quantifier": "generic"
   },
   {
    "trial_type": "critical",
    "page_type": "text",
    "condition": "interrupted",
    "chapter_num": 3,
    "page_num": 2,
    "page_content": "and enjoy the sunshine there.",
    "query_predicate_1": "live on the continent of Caro",
    "response_1": -99,
    "rt": 5547,
    "kind": "glippets",
    "predicate_1": "live on the continent of Caro",
    "question_order": "NA",
    "chapter": "Glippets",
    "quantifier": "generic"
   },
   {
    "trial_type": "filler",
    "page_type": "text",
    "condition": "interrupted",
    "chapter_num": 4,
    "page_num": 0,
    "page_content": "Yomis are small, fast insect-like creatures. They all live in the ",
    "query_predicate_1": "live on the continent of Caro",
    "response_1": -99,
    "rt": 5231,
    "kind": "yomis",
    "predicate_1": "live in the borderland woodlands",
    "question_order": "NA",
    "chapter": "Yomis",
    "quantifier": "all"
   },
   {
    "trial_type": "filler",
    "page_type": "text",
    "condition": "interrupted",
    "chapter_num": 4,
    "page_num": 1,
    "page_content": "borderland woodlands. They all fly towards the mountains in search of food, but they need to be careful ",
    "query_predicate_1": "live on the continent of Caro",
    "response_1": -99,
    "rt": 4218,
    "kind": "yomis",
    "predicate_1": "live in the borderland woodlands",
    "question_order": "NA",
    "chapter": "Yomis",
    "quantifier": "all"
   },
   {
    "trial_type": "filler",
    "page_type": "query",
    "condition": "interrupted",
    "chapter_num": 4,
    "page_num": -1,
    "page_content": "",
    "query_predicate_1": "live in the borderland woodlands",
    "response_1": 1,
    "rt": 8607,
    "kind": "yomis",
    "predicate_1": "live in the borderland woodlands",
    "question_order": "NA",
    "chapter": "Yomis",
    "quantifier": "all"
   },
   {
    "trial_type": "filler",
    "page_type": "text",
    "condition": "interrupted",
    "chapter_num": 4,
    "page_num": 2,
    "page_content": "of their natural predators, turmens.",
    "query_predicate_1": "live in the borderland woodlands",
    "response_1": -99,
    "rt": 5445,
    "kind": "yomis",
    "predicate_1": "live in the borderland woodlands",
    "question_order": "NA",
    "chapter": "Yomis",
    "quantifier": "all"
   },
   {
    "trial_type": "critical",
    "page_type": "text",
    "condition": "uninterrupted",
    "chapter_num": 5,
    "page_num": 0,
    "page_content": "Reesles are strange, furry creatures, often found in the homes of the aliens. They are not house pets ",
    "query_predicate_1": "live in the borderland woodlands",
    "response_1": -99,
    "rt": 4409,
    "kind": "reesles",
    "predicate_1": "wear wutsats around their heads",
    "question_order": "NA",
    "chapter": "Reesles",
    "quantifier": "generic"
   },
   {
    "trial_type": "critical",
    "page_type": "text",
    "condition": "uninterrupted",
    "chapter_num": 5,
    "page_num": 1,
    "page_content": "but quasi-domesticated animals. They will steal food from you if you are not paying attention. They have",
    "query_predicate_1": "live in the borderland woodlands",
    "response_1": -99,
    "rt": 4096,
    "kind": "reesles",
    "predicate_1": "wear wutsats around their heads",
    "question_order": "NA",
    "chapter": "Reesles",
    "quantifier": "generic"
   },
   {
    "trial_type": "critical",
    "page_type": "text",
    "condition": "uninterrupted",
    "chapter_num": 5,
    "page_num": 2,
    "page_content": "special headgear to help other aliens identify their owners. Around their heads, they wear giant wutsats",
    "query_predicate_1": "live in the borderland woodlands",
    "response_1": -99,
    "rt": 5456,
    "kind": "reesles",
    "predicate_1": "wear wutsats around their heads",
    "question_order": "NA",
    "chapter": "Reesles",
    "quantifier": "generic"
   },
   {
    "trial_type": "critical",
    "page_type": "text",
    "condition": "uninterrupted",
    "chapter_num": 5,
    "page_num": 3,
    "page_content": "and krevnors.",
    "query_predicate_1": "live in the borderland woodlands",
    "response_1": -99,
    "rt": 2880,
    "kind": "reesles",
    "predicate_1": "wear wutsats around their heads",
    "question_order": "NA",
    "chapter": "Reesles",
    "quantifier": "generic"
   },
   {
    "trial_type": "critical",
    "page_type": "query",
    "condition": "uninterrupted",
    "chapter_num": 5,
    "page_num": 4,
    "page_content": "",
    "query_predicate_1": "wear wutsats around their heads",
    "response_1": 0.8,
    "rt": 42775,
    "kind": "reesles",
    "predicate_1": "wear wutsats around their heads",
    "question_order": "NA",
    "chapter": "Reesles",
    "quantifier": "generic"
   },
   {
    "trial_type": "critical",
    "page_type": "text",
    "condition": "nme_uninterrupted",
    "chapter_num": 6,
    "page_num": 0,
    "page_content": "Vimbles are social insects that live in colonies of up to a thousand individuals. Vimbles live for a year ",
    "query_predicate_1": "wear wutsats around their heads",
    "response_1": -99,
    "rt": 8336,
    "kind": "vimble queens",
    "predicate_1": "hibernate in fallen logs",
    "question_order": "NA",
    "chapter": "Vimbles",
    "quantifier": "generic"
   },
   {
    "trial_type": "critical",
    "page_type": "text",
    "condition": "nme_uninterrupted",
    "chapter_num": 6,
    "page_num": 1,
    "page_content": "or less. They have a single queen, who must find somewhere to hibernate over the winter before ",
    "query_predicate_1": "wear wutsats around their heads",
    "response_1": -99,
    "rt": 5311,
    "kind": "vimble queens",
    "predicate_1": "hibernate in fallen logs",
    "question_order": "NA",
    "chapter": "Vimbles",
    "quantifier": "generic"
   },
   {
    "trial_type": "critical",
    "page_type": "text",
    "condition": "nme_uninterrupted",
    "chapter_num": 6,
    "page_num": 2,
    "page_content": "starting a new colony. Vimble queens hibernate in fallen logs  ",
    "query_predicate_1": "wear wutsats around their heads",
    "response_1": -99,
    "rt": 3093,
    "kind": "vimble queens",
    "predicate_1": "hibernate in fallen logs",
    "question_order": "NA",
    "chapter": "Vimbles",
    "quantifier": "generic"
   },
   {
    "trial_type": "critical",
    "page_type": "text",
    "condition": "nme_uninterrupted",
    "chapter_num": 6,
    "page_num": 3,
    "page_content": "and give birth twice a year.",
    "query_predicate_1": "wear wutsats around their heads",
    "response_1": -99,
    "rt": 2352,
    "kind": "vimble queens",
    "predicate_1": "hibernate in fallen logs",
    "question_order": "NA",
    "chapter": "Vimbles",
    "quantifier": "generic"
   },
   {
    "trial_type": "critical",
    "page_type": "query",
    "condition": "nme_uninterrupted",
    "chapter_num": 6,
    "page_num": 4,
    "page_content": "",
    "query_predicate_1": "hibernate in fallen logs",
    "response_1": 1,
    "rt": 9000,
    "kind": "vimble queens",
    "predicate_1": "hibernate in fallen logs",
    "question_order": "NA",
    "chapter": "Vimbles",
    "quantifier": "generic"
   },
   {
    "trial_type": "critical",
    "page_type": "text",
    "condition": "uninterrupted",
    "chapter_num": 7,
    "page_num": 0,
    "page_content": "Mooks are ferocious creatures that live on the continent of Benli. Benli has dramatic elevation changes ",
    "query_predicate_1": "hibernate in fallen logs",
    "response_1": -99,
    "rt": 5862,
    "kind": "mooks",
    "predicate_1": "have territories at the tops of tall mountains",
    "question_order": "NA",
    "chapter": "Mooks",
    "quantifier": "generic"
   },
   {
    "trial_type": "critical",
    "page_type": "text",
    "condition": "uninterrupted",
    "chapter_num": 7,
    "page_num": 1,
    "page_content": "unlike any other continent on Dax. Animals find terrority in locations that will maximize their chances ",
    "query_predicate_1": "hibernate in fallen logs",
    "response_1": -99,
    "rt": 3646,
    "kind": "mooks",
    "predicate_1": "have territories at the tops of tall mountains",
    "question_order": "NA",
    "chapter": "Mooks",
    "quantifier": "generic"
   },
   {
    "trial_type": "critical",
    "page_type": "text",
    "condition": "uninterrupted",
    "chapter_num": 7,
    "page_num": 2,
    "page_content": "of survival. Mooks have territories at the tops of tall mountains",
    "query_predicate_1": "hibernate in fallen logs",
    "response_1": -99,
    "rt": 4206,
    "kind": "mooks",
    "predicate_1": "have territories at the tops of tall mountains",
    "question_order": "NA",
    "chapter": "Mooks",
    "quantifier": "generic"
   },
   {
    "trial_type": "critical",
    "page_type": "text",
    "condition": "uninterrupted",
    "chapter_num": 7,
    "page_num": 3,
    "page_content": "and at the bottom of deep canyons.",
    "query_predicate_1": "hibernate in fallen logs",
    "response_1": -99,
    "rt": 2487,
    "kind": "mooks",
    "predicate_1": "have territories at the tops of tall mountains",
    "question_order": "NA",
    "chapter": "Mooks",
    "quantifier": "generic"
   },
   {
    "trial_type": "critical",
    "page_type": "query",
    "condition": "uninterrupted",
    "chapter_num": 7,
    "page_num": 4,
    "page_content": "",
    "query_predicate_1": "have territories at the tops of tall mountains",
    "response_1": 0.5,
    "rt": 18383,
    "kind": "mooks",
    "predicate_1": "have territories at the tops of tall mountains",
    "question_order": "NA",
    "chapter": "Mooks",
    "quantifier": "generic"
   },
   {
    "trial_type": "filler",
    "page_type": "text",
    "condition": "uninterrupted",
    "chapter_num": 8,
    "page_num": 0,
    "page_content": "Zorf the mapmaker lives in the large forest city of Astom. In Astom, there are many ways to get",
    "query_predicate_1": "have territories at the tops of tall mountains",
    "response_1": -99,
    "rt": 3959,
    "kind": "Astom aliens",
    "predicate_1": "use the tunnels to get around town",
    "question_order": "NA",
    "chapter": "Zorf the mapmaker",
    "quantifier": "all"
   },
   {
    "trial_type": "filler",
    "page_type": "text",
    "condition": "uninterrupted",
    "chapter_num": 8,
    "page_num": 1,
    "page_content": "from place to place, but the most popular way is through tunnels. All of the Astom aliens use the tunnels",
    "query_predicate_1": "have territories at the tops of tall mountains",
    "response_1": -99,
    "rt": 3657,
    "kind": "Astom aliens",
    "predicate_1": "use the tunnels to get around town",
    "question_order": "NA",
    "chapter": "Zorf the mapmaker",
    "quantifier": "all"
   },
   {
    "trial_type": "filler",
    "page_type": "text",
    "condition": "uninterrupted",
    "chapter_num": 8,
    "page_num": 2,
    "page_content": "to get around town from their homes in the residential quarter. Since all of the Astom aliens live there, it's peaceful during the day ",
    "query_predicate_1": "have territories at the tops of tall mountains",
    "response_1": -99,
    "rt": 3453,
    "kind": "Astom aliens",
    "predicate_1": "use the tunnels to get around town",
    "question_order": "NA",
    "chapter": "Zorf the mapmaker",
    "quantifier": "all"
   },
   {
    "trial_type": "filler",
    "page_type": "text",
    "condition": "uninterrupted",
    "chapter_num": 8,
    "page_num": 3,
    "page_content": "but very crowded at night.",
    "query_predicate_1": "have territories at the tops of tall mountains",
    "response_1": -99,
    "rt": 1283,
    "kind": "Astom aliens",
    "predicate_1": "use the tunnels to get around town",
    "question_order": "NA",
    "chapter": "Zorf the mapmaker",
    "quantifier": "all"
   },
   {
    "trial_type": "filler",
    "page_type": "query",
    "condition": "uninterrupted",
    "chapter_num": 8,
    "page_num": 4,
    "page_content": "",
    "query_predicate_1": "use the tunnels to get around town",
    "response_1": 1,
    "rt": 3161,
    "kind": "Astom aliens",
    "predicate_1": "use the tunnels to get around town",
    "question_order": "NA",
    "chapter": "Zorf the mapmaker",
    "quantifier": "all"
   },
   {
    "trial_type": "critical",
    "page_type": "text",
    "condition": "nme_interrupted",
    "chapter_num": 9,
    "page_num": 0,
    "page_content": "Lorches have massive beaks and are found on the continents of Dodi and Gomi. The two continents",
    "query_predicate_1": "use the tunnels to get around town",
    "response_1": -99,
    "rt": 4117,
    "kind": "lorches",
    "predicate_1": "have long wings",
    "question_order": "NA",
    "chapter": "Lorches",
    "quantifier": "generic"
   },
   {
    "trial_type": "critical",
    "page_type": "text",
    "condition": "nme_interrupted",
    "chapter_num": 9,
    "page_num": 1,
    "page_content": "are quite different in what kinds of animals are available for them to eat. Lorches have long wings ",
    "query_predicate_1": "use the tunnels to get around town",
    "response_1": -99,
    "rt": 3488,
    "kind": "lorches",
    "predicate_1": "have long wings",
    "question_order": "NA",
    "chapter": "Lorches",
    "quantifier": "generic"
   },
   {
    "trial_type": "critical",
    "page_type": "query",
    "condition": "nme_interrupted",
    "chapter_num": 9,
    "page_num": -1,
    "page_content": "",
    "query_predicate_1": "have long wings",
    "response_1": 1,
    "rt": 3375,
    "kind": "lorches",
    "predicate_1": "have long wings",
    "question_order": "NA",
    "chapter": "Lorches",
    "quantifier": "generic"
   },
   {
    "trial_type": "critical",
    "page_type": "text",
    "condition": "nme_interrupted",
    "chapter_num": 9,
    "page_num": 2,
    "page_content": "and fly only at night.",
    "query_predicate_1": "have long wings",
    "response_1": -99,
    "rt": 1440,
    "kind": "lorches",
    "predicate_1": "have long wings",
    "question_order": "NA",
    "chapter": "Lorches",
    "quantifier": "generic"
   },
   {
    "trial_type": "filler",
    "page_type": "text",
    "condition": "interrupted",
    "chapter_num": 10,
    "page_num": 0,
    "page_content": "The morseth is an animal that lives part of its life in the sea and part of its life on land. Most morseths ",
    "query_predicate_1": "have long wings",
    "response_1": -99,
    "rt": 6401,
    "kind": "morseths",
    "predicate_1": "build permanent structures called fendles",
    "question_order": "NA",
    "chapter": "Morseths",
    "quantifier": "most"
   },
   {
    "trial_type": "filler",
    "page_type": "text",
    "condition": "interrupted",
    "chapter_num": 10,
    "page_num": 1,
    "page_content": "come on land to find mates and to bury their dead. Most morseths build permanent structures called fendles in order to bury their dead ",
    "query_predicate_1": "have long wings",
    "response_1": -99,
    "rt": 5918,
    "kind": "morseths",
    "predicate_1": "build permanent structures called fendles",
    "question_order": "NA",
    "chapter": "Morseths",
    "quantifier": "most"
   },
   {
    "trial_type": "filler",
    "page_type": "query",
    "condition": "interrupted",
    "chapter_num": 10,
    "page_num": -1,
    "page_content": "",
    "query_predicate_1": "build permanent structures called fendles",
    "response_1": 0.85,
    "rt": 5682,
    "kind": "morseths",
    "predicate_1": "build permanent structures called fendles",
    "question_order": "NA",
    "chapter": "Morseths",
    "quantifier": "most"
   },
   {
    "trial_type": "filler",
    "page_type": "text",
    "condition": "interrupted",
    "chapter_num": 10,
    "page_num": 2,
    "page_content": "kin, and fendles are usually made out of wood.",
    "query_predicate_1": "build permanent structures called fendles",
    "response_1": -99,
    "rt": 3498,
    "kind": "morseths",
    "predicate_1": "build permanent structures called fendles",
    "question_order": "NA",
    "chapter": "Morseths",
    "quantifier": "most"
   },
   {
    "trial_type": "critical",
    "page_type": "text",
    "condition": "uninterrupted",
    "chapter_num": 11,
    "page_num": 0,
    "page_content": "The aliens have many different kinds of specialized skills and trades, such as basket weaving. Crafters are found all over Dax, but ",
    "query_predicate_1": "build permanent structures called fendles",
    "response_1": -99,
    "rt": 5523,
    "kind": "basket weavers",
    "predicate_1": "are part of the Tinno guild",
    "question_order": "NA",
    "chapter": "Crafts",
    "quantifier": "generic"
   },
   {
    "trial_type": "critical",
    "page_type": "text",
    "condition": "uninterrupted",
    "chapter_num": 11,
    "page_num": 1,
    "page_content": "they are especially common in the city of Rondoo, where aliens from all over go to buy luxury goods. To ",
    "query_predicate_1": "build permanent structures called fendles",
    "response_1": -99,
    "rt": 3961,
    "kind": "basket weavers",
    "predicate_1": "are part of the Tinno guild",
    "question_order": "NA",
    "chapter": "Crafts",
    "quantifier": "generic"
   },
   {
    "trial_type": "critical",
    "page_type": "text",
    "condition": "uninterrupted",
    "chapter_num": 11,
    "page_num": 2,
    "page_content": "help make themselves known, crafters join guilds with other crafters of the same trade. Basket weavers are part of the Tinno guild ",
    "query_predicate_1": "build permanent structures called fendles",
    "response_1": -99,
    "rt": 4365,
    "kind": "basket weavers",
    "predicate_1": "are part of the Tinno guild",
    "question_order": "NA",
    "chapter": "Crafts",
    "quantifier": "generic"
   },
   {
    "trial_type": "critical",
    "page_type": "text",
    "condition": "uninterrupted",
    "chapter_num": 11,
    "page_num": 3,
    "page_content": "and the Farza guild.",
    "query_predicate_1": "build permanent structures called fendles",
    "response_1": -99,
    "rt": 1631,
    "kind": "basket weavers",
    "predicate_1": "are part of the Tinno guild",
    "question_order": "NA",
    "chapter": "Crafts",
    "quantifier": "generic"
   },
   {
    "trial_type": "critical",
    "page_type": "query",
    "condition": "uninterrupted",
    "chapter_num": 11,
    "page_num": 4,
    "page_content": "",
    "query_predicate_1": "are part of the Tinno guild",
    "response_1": 0.5,
    "rt": 3881,
    "kind": "basket weavers",
    "predicate_1": "are part of the Tinno guild",
    "question_order": "NA",
    "chapter": "Crafts",
    "quantifier": "generic"
   },
   {
    "trial_type": "filler",
    "page_type": "text",
    "condition": "uninterrupted",
    "chapter_num": 12,
    "page_num": 0,
    "page_content": "The weather on Dax is very constant, not changing much from day to day. Occasionally, there will ",
    "query_predicate_1": "are part of the Tinno guild",
    "response_1": -99,
    "rt": 3364,
    "kind": "ice storms on Dax",
    "predicate_1": "result in permanent damage to the plants and animals on Dax",
    "question_order": "NA",
    "chapter": "Weather",
    "quantifier": "none"
   },
   {
    "trial_type": "filler",
    "page_type": "text",
    "condition": "uninterrupted",
    "chapter_num": 12,
    "page_num": 1,
    "page_content": "be tremendous ice storms that freeze over the entire planet. These ice storms never last long ",
    "query_predicate_1": "are part of the Tinno guild",
    "response_1": -99,
    "rt": 3982,
    "kind": "ice storms on Dax",
    "predicate_1": "result in permanent damage to the plants and animals on Dax",
    "question_order": "NA",
    "chapter": "Weather",
    "quantifier": "none"
   },
   {
    "trial_type": "filler",
    "page_type": "text",
    "condition": "uninterrupted",
    "chapter_num": 12,
    "page_num": 2,
    "page_content": " or result in permanent damage to the plants and animals on Dax. However, the ice storms make the entire sky as dark as night",
    "query_predicate_1": "are part of the Tinno guild",
    "response_1": -99,
    "rt": 4354,
    "kind": "ice storms on Dax",
    "predicate_1": "result in permanent damage to the plants and animals on Dax",
    "question_order": "NA",
    "chapter": "Weather",
    "quantifier": "none"
   },
   {
    "trial_type": "filler",
    "page_type": "text",
    "condition": "uninterrupted",
    "chapter_num": 12,
    "page_num": 3,
    "page_content": " and they frighten most of the animals on Dax.",
    "query_predicate_1": "are part of the Tinno guild",
    "response_1": -99,
    "rt": 2711,
    "kind": "ice storms on Dax",
    "predicate_1": "result in permanent damage to the plants and animals on Dax",
    "question_order": "NA",
    "chapter": "Weather",
    "quantifier": "none"
   },
   {
    "trial_type": "filler",
    "page_type": "query",
    "condition": "uninterrupted",
    "chapter_num": 12,
    "page_num": 4,
    "page_content": "",
    "query_predicate_1": "result in permanent damage to the plants and animals on Dax",
    "response_1": 0,
    "rt": 8157,
    "kind": "ice storms on Dax",
    "predicate_1": "result in permanent damage to the plants and animals on Dax",
    "question_order": "NA",
    "chapter": "Weather",
    "quantifier": "none"
   },
   {
    "trial_type": "critical",
    "page_type": "text",
    "condition": "interrupted",
    "chapter_num": 13,
    "page_num": 0,
    "page_content": "Kweps hunt in packs. Even though they are pack animals, all of them have highly idiosyncractic food ",
    "query_predicate_1": "result in permanent damage to the plants and animals on Dax",
    "response_1": -99,
    "rt": 14097,
    "kind": "kweps",
    "predicate_1": "chew on xorfun",
    "question_order": "NA",
    "chapter": "Kweps",
    "quantifier": "generic"
   },
   {
    "trial_type": "critical",
    "page_type": "text",
    "condition": "interrupted",
    "chapter_num": 13,
    "page_num": 1,
    "page_content": "preferences and behaviors. Some of them like to eat apples and others like to eat oranges. When they go ",
    "query_predicate_1": "result in permanent damage to the plants and animals on Dax",
    "response_1": -99,
    "rt": 3971,
    "kind": "kweps",
    "predicate_1": "chew on xorfun",
    "question_order": "NA",
    "chapter": "Kweps",
    "quantifier": "generic"
   },
   {
    "trial_type": "critical",
    "page_type": "text",
    "condition": "interrupted",
    "chapter_num": 13,
    "page_num": 2,
    "page_content": "hunting at night they look for creatures sleeping alone, not in groups. Right before they go hunting, the kweps chew on xorfun",
    "query_predicate_1": "result in permanent damage to the plants and animals on Dax",
    "response_1": -99,
    "rt": 4883,
    "kind": "kweps",
    "predicate_1": "chew on xorfun",
    "question_order": "NA",
    "chapter": "Kweps",
    "quantifier": "generic"
   },
   {
    "trial_type": "critical",
    "page_type": "query",
    "condition": "interrupted",
    "chapter_num": 13,
    "page_num": -1,
    "page_content": "",
    "query_predicate_1": "chew on xorfun",
    "response_1": 1,
    "rt": 27980,
    "kind": "kweps",
    "predicate_1": "chew on xorfun",
    "question_order": "NA",
    "chapter": "Kweps",
    "quantifier": "generic"
   },
   {
    "trial_type": "critical",
    "page_type": "text",
    "condition": "interrupted",
    "chapter_num": 13,
    "page_num": 3,
    "page_content": "and howl towards the sky.",
    "query_predicate_1": "chew on xorfun",
    "response_1": -99,
    "rt": 1282,
    "kind": "kweps",
    "predicate_1": "chew on xorfun",
    "question_order": "NA",
    "chapter": "Kweps",
    "quantifier": "generic"
   },
   {
    "trial_type": "critical",
    "page_type": "text",
    "condition": "nme_uninterrupted",
    "chapter_num": 14,
    "page_num": 0,
    "page_content": "The Ludinos are an alien tribe. They are very industrious and live ",
    "query_predicate_1": "chew on xorfun",
    "response_1": -99,
    "rt": 3993,
    "kind": "Ludinos",
    "predicate_1": "ascribe to the Caboo religion",
    "question_order": "NA",
    "chapter": "Ludinos",
    "quantifier": "generic"
   },
   {
    "trial_type": "critical",
    "page_type": "text",
    "condition": "nme_uninterrupted",
    "chapter_num": 14,
    "page_num": 1,
    "page_content": "on all of the seven continents, and they all are highly spiritual. They ascribe to the Caboo religion",
    "query_predicate_1": "chew on xorfun",
    "response_1": -99,
    "rt": 4455,
    "kind": "Ludinos",
    "predicate_1": "ascribe to the Caboo religion",
    "question_order": "NA",
    "chapter": "Ludinos",
    "quantifier": "generic"
   },
   {
    "trial_type": "critical",
    "page_type": "text",
    "condition": "nme_uninterrupted",
    "chapter_num": 14,
    "page_num": 2,
    "page_content": "pray three times a day.",
    "query_predicate_1": "chew on xorfun",
    "response_1": -99,
    "rt": 1643,
    "kind": "Ludinos",
    "predicate_1": "ascribe to the Caboo religion",
    "question_order": "NA",
    "chapter": "Ludinos",
    "quantifier": "generic"
   },
   {
    "trial_type": "critical",
    "page_type": "query",
    "condition": "nme_uninterrupted",
    "chapter_num": 14,
    "page_num": 3,
    "page_content": "",
    "query_predicate_1": "ascribe to the Caboo religion",
    "response_1": 1,
    "rt": 3037,
    "kind": "Ludinos",
    "predicate_1": "ascribe to the Caboo religion",
    "question_order": "NA",
    "chapter": "Ludinos",
    "quantifier": "generic"
   },
   {
    "trial_type": "critical",
    "page_type": "text",
    "condition": "interrupted",
    "chapter_num": 15,
    "page_num": 0,
    "page_content": "Batozes are large birds that are found along all the coasts of Dax. They are skilled hunters and ",
    "query_predicate_1": "ascribe to the Caboo religion",
    "response_1": -99,
    "rt": 4173,
    "kind": "batozes",
    "predicate_1": "have six wings",
    "question_order": "NA",
    "chapter": "Batozes",
    "quantifier": "generic"
   },
   {
    "trial_type": "critical",
    "page_type": "text",
    "condition": "interrupted",
    "chapter_num": 15,
    "page_num": 1,
    "page_content": "can fly for whole days without stopping. They use their sharp claws to hunt for fish. They also ",
    "query_predicate_1": "ascribe to the Caboo religion",
    "response_1": -99,
    "rt": 4612,
    "kind": "batozes",
    "predicate_1": "have six wings",
    "question_order": "NA",
    "chapter": "Batozes",
    "quantifier": "generic"
   },
   {
    "trial_type": "critical",
    "page_type": "text",
    "condition": "interrupted",
    "chapter_num": 15,
    "page_num": 2,
    "page_content": "have special wings that are light but powerful. Batozes have six wings ",
    "query_predicate_1": "ascribe to the Caboo religion",
    "response_1": -99,
    "rt": 3105,
    "kind": "batozes",
    "predicate_1": "have six wings",
    "question_order": "NA",
    "chapter": "Batozes",
    "quantifier": "generic"
   },
   {
    "trial_type": "critical",
    "page_type": "query",
    "condition": "interrupted",
    "chapter_num": 15,
    "page_num": -1,
    "page_content": "",
    "query_predicate_1": "have six wings",
    "response_1": 1,
    "rt": 3027,
    "kind": "batozes",
    "predicate_1": "have six wings",
    "question_order": "NA",
    "chapter": "Batozes",
    "quantifier": "generic"
   },
   {
    "trial_type": "critical",
    "page_type": "text",
    "condition": "interrupted",
    "chapter_num": 15,
    "page_num": 3,
    "page_content": "and can flap their wings very fast.",
    "query_predicate_1": "have six wings",
    "response_1": -99,
    "rt": 1305,
    "kind": "batozes",
    "predicate_1": "have six wings",
    "question_order": "NA",
    "chapter": "Batozes",
    "quantifier": "generic"
   },
   {
    "trial_type": "filler",
    "page_type": "text",
    "condition": "uninterrupted",
    "chapter_num": 16,
    "page_num": 0,
    "page_content": "Zorxon is the overlord of Dax.  Everyone loves Zorxon because she ",
    "query_predicate_1": "have six wings",
    "response_1": -99,
    "rt": 5119,
    "kind": "aliens",
    "predicate_1": "love Zorxon",
    "question_order": "NA",
    "chapter": "Zorxon, overlord of Dax",
    "quantifier": "all"
   },
   {
    "trial_type": "filler",
    "page_type": "text",
    "condition": "uninterrupted",
    "chapter_num": 16,
    "page_num": 1,
    "page_content": "provides for all the aliens of Dax. However, Zorxon is now very old ",
    "query_predicate_1": "have six wings",
    "response_1": -99,
    "rt": 3251,
    "kind": "aliens",
    "predicate_1": "love Zorxon",
    "question_order": "NA",
    "chapter": "Zorxon, overlord of Dax",
    "quantifier": "all"
   },
   {
    "trial_type": "filler",
    "page_type": "text",
    "condition": "uninterrupted",
    "chapter_num": 16,
    "page_num": 2,
    "page_content": "and she rarely makes public appearances anymore. Still, she is very influential.",
    "query_predicate_1": "have six wings",
    "response_1": -99,
    "rt": 3488,
    "kind": "aliens",
    "predicate_1": "love Zorxon",
    "question_order": "NA",
    "chapter": "Zorxon, overlord of Dax",
    "quantifier": "all"
   },
   {
    "trial_type": "filler",
    "page_type": "query",
    "condition": "uninterrupted",
    "chapter_num": 16,
    "page_num": 3,
    "page_content": "",
    "query_predicate_1": "love Zorxon",
    "response_1": 1,
    "rt": 3026,
    "kind": "aliens",
    "predicate_1": "love Zorxon",
    "question_order": "NA",
    "chapter": "Zorxon, overlord of Dax",
    "quantifier": "all"
   },
   {
    "trial_type": "critical",
    "page_type": "text",
    "condition": "interrupted",
    "chapter_num": 17,
    "page_num": 0,
    "page_content": "Kaples are small animals that live in the jungles. They are most active ",
    "query_predicate_1": "love Zorxon",
    "response_1": -99,
    "rt": 2936,
    "kind": "kaples",
    "predicate_1": "have striped fur",
    "question_order": "NA",
    "chapter": "Kaples",
    "quantifier": "generic"
   },
   {
    "trial_type": "critical",
    "page_type": "text",
    "condition": "interrupted",
    "chapter_num": 17,
    "page_num": 1,
    "page_content": "at dawn and at dusk, when their usual predators are less active. Their thick fur helps camouflage ",
    "query_predicate_1": "love Zorxon",
    "response_1": -99,
    "rt": 4489,
    "kind": "kaples",
    "predicate_1": "have striped fur",
    "question_order": "NA",
    "chapter": "Kaples",
    "quantifier": "generic"
   },
   {
    "trial_type": "critical",
    "page_type": "text",
    "condition": "interrupted",
    "chapter_num": 17,
    "page_num": 2,
    "page_content": "them among the plants on the forest floor. Kaples have striped fur ",
    "query_predicate_1": "love Zorxon",
    "response_1": -99,
    "rt": 3375,
    "kind": "kaples",
    "predicate_1": "have striped fur",
    "question_order": "NA",
    "chapter": "Kaples",
    "quantifier": "generic"
   },
   {
    "trial_type": "critical",
    "page_type": "query",
    "condition": "interrupted",
    "chapter_num": 17,
    "page_num": -1,
    "page_content": "",
    "query_predicate_1": "have striped fur",
    "response_1": 1,
    "rt": 2881,
    "kind": "kaples",
    "predicate_1": "have striped fur",
    "question_order": "NA",
    "chapter": "Kaples",
    "quantifier": "generic"
   },
   {
    "trial_type": "critical",
    "page_type": "text",
    "condition": "interrupted",
    "chapter_num": 17,
    "page_num": 3,
    "page_content": "and beautiful eyes.",
    "query_predicate_1": "have striped fur",
    "response_1": -99,
    "rt": 1282,
    "kind": "kaples",
    "predicate_1": "have striped fur",
    "question_order": "NA",
    "chapter": "Kaples",
    "quantifier": "generic"
   },
   {
    "trial_type": "critical",
    "page_type": "text",
    "condition": "nme_interrupted",
    "chapter_num": 18,
    "page_num": 0,
    "page_content": "Krens are a tribe of the aliens that live on the continent of Benli, which has no agriculture. Like most ",
    "query_predicate_1": "have striped fur",
    "response_1": -99,
    "rt": 9552,
    "kind": "Krens",
    "predicate_1": "are stup-herders",
    "question_order": "NA",
    "chapter": "Finding food",
    "quantifier": "generic"
   },
   {
    "trial_type": "critical",
    "page_type": "text",
    "condition": "nme_interrupted",
    "chapter_num": 18,
    "page_num": 1,
    "page_content": "creatures on Dax, Krens eat other creatures to survive. Animals like stups, four-legged creatures with ",
    "query_predicate_1": "have striped fur",
    "response_1": -99,
    "rt": 5085,
    "kind": "Krens",
    "predicate_1": "are stup-herders",
    "question_order": "NA",
    "chapter": "Finding food",
    "quantifier": "generic"
   },
   {
    "trial_type": "critical",
    "page_type": "text",
    "condition": "nme_interrupted",
    "chapter_num": 18,
    "page_num": 2,
    "page_content": "large antlers, are a resource for the Krens. Stups roam all over the windy highlands of Benli, far from the oceans. Krens are stup-herders",
    "query_predicate_1": "have striped fur",
    "response_1": -99,
    "rt": 6356,
    "kind": "Krens",
    "predicate_1": "are stup-herders",
    "question_order": "NA",
    "chapter": "Finding food",
    "quantifier": "generic"
   },
   {
    "trial_type": "critical",
    "page_type": "query",
    "condition": "nme_interrupted",
    "chapter_num": 18,
    "page_num": -1,
    "page_content": "",
    "query_predicate_1": "are stup-herders",
    "response_1": 1,
    "rt": 4591,
    "kind": "Krens",
    "predicate_1": "are stup-herders",
    "question_order": "NA",
    "chapter": "Finding food",
    "quantifier": "generic"
   },
   {
    "trial_type": "critical",
    "page_type": "text",
    "condition": "nme_interrupted",
    "chapter_num": 18,
    "page_num": 3,
    "page_content": "and incorporate stups into their religion.",
    "query_predicate_1": "are stup-herders",
    "response_1": -99,
    "rt": 1766,
    "kind": "Krens",
    "predicate_1": "are stup-herders",
    "question_order": "NA",
    "chapter": "Finding food",
    "quantifier": "generic"
   },
   {
    "trial_type": "critical",
    "page_type": "text",
    "condition": "uninterrupted",
    "chapter_num": 19,
    "page_num": 0,
    "page_content": "Isooms are tree-like plants that are found in hilly regions of Fale. Their fruit is edible, and the aliens often ",
    "query_predicate_1": "are stup-herders",
    "response_1": -99,
    "rt": 5794,
    "kind": "isooms",
    "predicate_1": "produce fruit with bumpy skin",
    "question_order": "NA",
    "chapter": "Isooms",
    "quantifier": "generic"
   },
   {
    "trial_type": "critical",
    "page_type": "text",
    "condition": "uninterrupted",
    "chapter_num": 19,
    "page_num": 1,
    "page_content": "cultivate isooms for food. Isooms produce fruit with bumpy skin ",
    "query_predicate_1": "are stup-herders",
    "response_1": -99,
    "rt": 3206,
    "kind": "isooms",
    "predicate_1": "produce fruit with bumpy skin",
    "question_order": "NA",
    "chapter": "Isooms",
    "quantifier": "generic"
   },
   {
    "trial_type": "critical",
    "page_type": "text",
    "condition": "uninterrupted",
    "chapter_num": 19,
    "page_num": 2,
    "page_content": "and fruit with smooth skin.",
    "query_predicate_1": "are stup-herders",
    "response_1": -99,
    "rt": 1755,
    "kind": "isooms",
    "predicate_1": "produce fruit with bumpy skin",
    "question_order": "NA",
    "chapter": "Isooms",
    "quantifier": "generic"
   },
   {
    "trial_type": "critical",
    "page_type": "query",
    "condition": "uninterrupted",
    "chapter_num": 19,
    "page_num": 3,
    "page_content": "",
    "query_predicate_1": "produce fruit with bumpy skin",
    "response_1": 0.5,
    "rt": 3893,
    "kind": "isooms",
    "predicate_1": "produce fruit with bumpy skin",
    "question_order": "NA",
    "chapter": "Isooms",
    "quantifier": "generic"
   },
   {
    "trial_type": "filler",
    "page_type": "text",
    "condition": "interrupted",
    "chapter_num": 20,
    "page_num": 0,
    "page_content": "Wint lived a long time ago in the mountains. He loved to travel, and ",
    "query_predicate_1": "produce fruit with bumpy skin",
    "response_1": -99,
    "rt": 11543,
    "kind": "aliens",
    "predicate_1": "remember Wint",
    "question_order": "NA",
    "chapter": "Wint of the Mountains",
    "quantifier": "all"
   },
   {
    "trial_type": "filler",
    "page_type": "text",
    "condition": "interrupted",
    "chapter_num": 20,
    "page_num": 1,
    "page_content": "would often go as far as the oceans. But all aliens remember Wint and admire him because he was the one that found the lost city of Baff ",
    "query_predicate_1": "produce fruit with bumpy skin",
    "response_1": -99,
    "rt": 7729,
    "kind": "aliens",
    "predicate_1": "remember Wint",
    "question_order": "NA",
    "chapter": "Wint of the Mountains",
    "quantifier": "all"
   },
   {
    "trial_type": "filler",
    "page_type": "query",
    "condition": "interrupted",
    "chapter_num": 20,
    "page_num": -1,
    "page_content": "",
    "query_predicate_1": "remember Wint",
    "response_1": 0.9,
    "rt": 9473,
    "kind": "aliens",
    "predicate_1": "remember Wint",
    "question_order": "NA",
    "chapter": "Wint of the Mountains",
    "quantifier": "all"
   },
   {
    "trial_type": "filler",
    "page_type": "text",
    "condition": "interrupted",
    "chapter_num": 20,
    "page_num": 2,
    "page_content": "and that rescued the ancient alien artifact from the city.",
    "query_predicate_1": "remember Wint",
    "response_1": -99,
    "rt": 1789,
    "kind": "aliens",
    "predicate_1": "remember Wint",
    "question_order": "NA",
    "chapter": "Wint of the Mountains",
    "quantifier": "all"
   }
  ],
  "catch_trials": [
   {
    "condition": "practice",
    "check_index": 1,
    "property": "dogs bark",
    "tested_on": -1,
    "response": 0.95,
    "correct": true
   },
   {
    "condition": "practice",
    "check_index": 2,
    "property": "birds are male",
    "tested_on": -1,
    "response": 0.5,
    "correct": true
   },
   {
    "condition": "practice",
    "check_index": 2,
    "property": "cats get cancer",
    "tested_on": -1,
    "response": 0.12,
    "correct": true
   },
   {
    "condition": "practice",
    "check_index": 2,
    "property": "lions lay eggs",
    "tested_on": -1,
    "response": 0,
    "correct": true
   },
   {
    "condition": "memory_check",
    "check_index": 0,
    "property": "no kweps eat plants",
    "tested_on": 0,
    "response": 1,
    "correct": 0
   },
   {
    "condition": "memory_check",
    "check_index": 1,
    "property": "lorches have long legs and breathe underwater",
    "tested_on": 0,
    "response": 0,
    "correct": 1
   },
   {
    "condition": "memory_check",
    "check_index": 2,
    "property": "no ice storms on Dax result in permanent damage to the plants and animals on Dax",
    "tested_on": 1,
    "response": 1,
    "correct": 1
   },
   {
    "condition": "memory_check",
    "check_index": 3,
    "property": "cranoor is the king of all beings",
    "tested_on": 0,
    "response": 0,
    "correct": 1
   },
   {
    "condition": "memory_check",
    "check_index": 4,
    "property": "most morseths build permanent structures called fendles",
    "tested_on": 1,
    "response": 0,
    "correct": 0
   },
   {
    "condition": "memory_check",
    "check_index": 5,
    "property": "all aliens love Zorxon",
    "tested_on": 1,
    "response": 1,
    "correct": 1
   },
   {
    "condition": "memory_check",
    "check_index": 6,
    "property": "dorbs have infected, yellow scales ",
    "tested_on": 0,
    "response": 0,
    "correct": 1
   },
   {
    "condition": "memory_check",
    "check_index": 7,
    "property": "all aliens remember Wint",
    "tested_on": 1,
    "response": 1,
    "correct": 1
   },
   {
    "condition": "memory_check",
    "check_index": 8,
    "property": "taifles have gold spots that are sticky",
    "tested_on": 0,
    "response": 0,
    "correct": 1
   },
   {
    "condition": "memory_check",
    "check_index": 9,
    "property": "all yomis live in the borderland woodlands",
    "tested_on": 1,
    "response": 0,
    "correct": 0
   },
   {
    "condition": "explanation",
    "check_index": -1,
    "property": "Answered questions related to content in the story and estimated the percentage of what was asked. The questions were asked after each chapter and I had to think about how many of the animals had the specific property.",
    "tested_on": -1,
    "response": -1,
    "correct": -1
   }
  ],
  "system": {
   "Browser": "Chrome",
   "OS": "Mac",
   "screenH": 1152,
   "screenW": 2048
  },
  "subject_information": {
   "language": "English",
   "enjoyment": "1",
   "asses": "Yes",
   "age": "56",
   "gender": "Male",
   "education": "4",
   "problems": "None",
   "fairprice": "Yes",
   "comments": ""
  },
  "time_in_minutes": 15.925833333333333
 }
}